{"artifacts":[],"artifactRelationships":[],"files":[{"id":"42e406108a36cb08","location":{"path":"/bin/axolotl"},"executable":{"format":"elf","hasExports":false,"hasEntrypoint":false,"importedLibraries":[]},"unknowns":["cargo-auditable-binary-cataloger: rust cataloger: unable to read dependency information: unknown file format","file-executable-cataloger: unable to determine ELF features: EOF","unknowns-labeler: no package identified in executable file"]},{"id":"30397843e6289b64","location":{"path":"/bin/crayfish"},"executable":{"format":"elf","hasExports":false,"hasEntrypoint":false,"importedLibraries":[]},"unknowns":["cargo-auditable-binary-cataloger: rust cataloger: unable to read dependency information: unknown file format","file-executable-cataloger: unable to determine ELF features: EOF","unknowns-labeler: no package identified in executable file"]},{"id":"073d12ddd0f0dc21","location":{"path":"/usr/lib/libzkgroup_linux_x86_64.so"},"executable":{"format":"elf","hasExports":false,"hasEntrypoint":false,"importedLibraries":[]},"unknowns":["cargo-auditable-binary-cataloger: rust cataloger: unable to read dependency information: unknown file format","file-executable-cataloger: unable to determine ELF features: EOF","unknowns-labeler: no package identified in executable file"]},{"id":"158b1e17c1fc77fc","location":{"path":"/usr/lib/x86_64-linux-gnu/libX11-xcb.so.1.0.0"},"executable":{"format":"elf","hasExports":false,"hasEntrypoint":false,"importedLibraries":[]},"unknowns":["cargo-auditable-binary-cataloger: rust cataloger: unable to read dependency information: unknown file format","file-executable-cataloger: unable to determine ELF features: EOF","unknowns-labeler: no package identified in executable file"]},{"id":"53421c1743ea1629","location":{"path":"/usr/lib/x86_64-linux-gnu/libX11.so.6.3.0"},"executable":{"format":"elf","hasExports":false,"hasEntrypoint":false,"importedLibraries":[]},"unknowns":["cargo-auditable-binary-cataloger: rust cataloger: unable to read dependency information: unknown file format","file-executable-cataloger: unable to determine ELF features: EOF","unknowns-labeler: no package identified in executable file"]},{"id":"e0f51d6488672190","location":{"path":"/usr/lib/x86_64-linux-gnu/libXau.so.6.0.0"},"executable":{"format":"elf","hasExports":false,"hasEntrypoint":false,"importedLibraries":[]},"unknowns":["cargo-auditable-binary-cataloger: rust cataloger: unable to read dependency information: unknown file format","file-executable-cataloger: unable to determine ELF features: EOF","unknowns-labeler: no package identified in executable file"]},{"id":"ac988b65e7936663","location":{"path":"/usr/lib/x86_64-linux-gnu/libXdmcp.so.6.0.0"},"executable":{"format":"elf","hasExports":false,"hasEntrypoint":false,"importedLibraries":[]},"unknowns":["cargo-auditable-binary-cataloger: rust cataloger: unable to read dependency information: unknown file format","file-executable-cataloger: unable to determine ELF features: EOF","unknowns-labeler: no package identified in executable file"]},{"id":"58671fceb888a868","location":{"path":"/usr/lib/x86_64-linux-gnu/libXext.so.6.4.0"},"executable":{"format":"elf","hasExports":false,"hasEntrypoint":false,"importedLibraries":[]},"unknowns":["cargo-auditable-binary-cataloger: rust cataloger: unable to read dependency information: unknown file format","file-executable-cataloger: unable to determine ELF features: EOF","unknowns-labeler: no package identified in executable file"]},{"id":"7b4c644ea4d6248e","location":{"path":"/usr/lib/x86_64-linux-gnu/libXss.so.1.0.0"},"executable":{"format":"elf","hasExports":false,"hasEntrypoint":false,"importedLibraries":[]},"unknowns":["cargo-auditable-binary-cataloger: rust cataloger: unable to read dependency information: unknown file format","file-executable-cataloger: unable to determine ELF features: EOF","unknowns-labeler: no package identified in executable file"]},{"id":"a9db0486bfc42511","location":{"path":"/usr/lib/x86_64-linux-gnu/libXtst.so.6.1.0"},"executable":{"format":"elf","hasExports":false,"hasEntrypoint":false,"importedLibraries":[]},"unknowns":["cargo-auditable-binary-cataloger: rust cataloger: unable to read dependency information: unknown file format","file-executable-cataloger: unable to determine ELF features: EOF","unknowns-labeler: no package identified in executable file"]},{"id":"54ceb8cfe80ccbc1","location":{"path":"/usr/lib/x86_64-linux-gnu/libasound.so.2.0.0"},"executable":{"format":"elf","hasExports":false,"hasEntrypoint":false,"importedLibraries":[]},"unknowns":["cargo-auditable-binary-cataloger: rust cataloger: unable to read dependency information: unknown file format","file-executable-cataloger: unable to determine ELF features: EOF","unknowns-labeler: no package identified in executable file"]},{"id":"8046e0d397a75e4e","location":{"path":"/usr/lib/x86_64-linux-gnu/libdbus-glib-1.so.2.3.4"},"executable":{"format":"elf","hasExports":false,"hasEntrypoint":false,"importedLibraries":[]},"unknowns":["cargo-auditable-binary-cataloger: rust cataloger: unable to read dependency information: unknown file format","file-executable-cataloger: unable to determine ELF features: EOF","unknowns-labeler: no package identified in executable file"]},{"id":"cf6f0e5f5f6f5b8c","location":{"path":"/usr/lib/x86_64-linux-gnu/libgconf-2.so.4.1.5"},"executable":{"format":"elf","hasExports":false,"hasEntrypoint":false,"importedLibraries":[]},"unknowns":["cargo-auditable-binary-cataloger: rust cataloger: unable to read dependency information: unknown file format","file-executable-cataloger: unable to determine ELF features: EOF","unknowns-labeler: no package identified in executable file"]},{"id":"28a978c55cf35c5c","location":{"path":"/usr/lib/x86_64-linux-gnu/libnspr4.so"},"executable":{"format":"elf","hasExports":false,"hasEntrypoint":false,"importedLibraries":[]},"unknowns":["cargo-auditable-binary-cataloger: rust cataloger: unable to read dependency information: unknown file format","file-executable-cataloger: unable to determine ELF features: EOF","unknowns-labeler: no package identified in executable file"]},{"id":"a183ab783567bc34","location":{"path":"/usr/lib/x86_64-linux-gnu/libnss3.so"},"executable":{"format":"elf","hasExports":false,"hasEntrypoint":false,"importedLibraries":[]},"unknowns":["cargo-auditable-binary-cataloger: rust cataloger: unable to read dependency information: unknown file format","file-executable-cataloger: unable to determine ELF features: EOF","unknowns-labeler: no package identified in executable file"]},{"id":"d4c76ff79ee8e046","location":{"path":"/usr/lib/x86_64-linux-gnu/libnssutil3.so"},"executable":{"format":"elf","hasExports":false,"hasEntrypoint":false,"importedLibraries":[]},"unknowns":["cargo-auditable-binary-cataloger: rust cataloger: unable to read dependency information: unknown file format","file-executable-cataloger: unable to determine ELF features: EOF","unknowns-labeler: no package identified in executable file"]},{"id":"7b238ff75091a80c","location":{"path":"/usr/lib/x86_64-linux-gnu/libplc4.so"},"executable":{"format":"elf","hasExports":false,"hasEntrypoint":false,"importedLibraries":[]},"unknowns":["cargo-auditable-binary-cataloger: rust cataloger: unable to read dependency information: unknown file format","file-executable-cataloger: unable to determine ELF features: EOF","unknowns-labeler: no package identified in executable file"]},{"id":"5f0de5086cbbe31c","location":{"path":"/usr/lib/x86_64-linux-gnu/libplds4.so"},"executable":{"format":"elf","hasExports":false,"hasEntrypoint":false,"importedLibraries":[]},"unknowns":["cargo-auditable-binary-cataloger: rust cataloger: unable to read dependency information: unknown file format","file-executable-cataloger: unable to determine ELF features: EOF","unknowns-labeler: no package identified in executable file"]},{"id":"a5e69372c991e3d9","location":{"path":"/usr/lib/x86_64-linux-gnu/libsmime3.so"},"executable":{"format":"elf","hasExports":false,"hasEntrypoint":false,"importedLibraries":[]},"unknowns":["cargo-auditable-binary-cataloger: rust cataloger: unable to read dependency information: unknown file format","file-executable-cataloger: unable to determine ELF features: EOF","unknowns-labeler: no package identified in executable file"]},{"id":"e65ce7e881d15ba6","location":{"path":"/usr/lib/x86_64-linux-gnu/libssl3.so"},"executable":{"format":"elf","hasExports":false,"hasEntrypoint":false,"importedLibraries":[]},"unknowns":["cargo-auditable-binary-cataloger: rust cataloger: unable to read dependency information: unknown file format","file-executable-cataloger: unable to determine ELF features: EOF","unknowns-labeler: no package identified in executable file"]},{"id":"7f7e399a1a78f734","location":{"path":"/usr/lib/x86_64-linux-gnu/libxcb.so.1.1.0"},"executable":{"format":"elf","hasExports":false,"hasEntrypoint":false,"importedLibraries":[]},"unknowns":["cargo-auditable-binary-cataloger: rust cataloger: unable to read dependency information: unknown file format","file-executable-cataloger: unable to determine ELF features: EOF","unknowns-labeler: no package identified in executable file"]},{"id":"1fd7451ac67d15d9","location":{"path":"/usr/lib/x86_64-linux-gnu/nss/libfreebl3.so"},"executable":{"format":"elf","hasExports":false,"hasEntrypoint":false,"importedLibraries":[]},"unknowns":["cargo-auditable-binary-cataloger: rust cataloger: unable to read dependency information: unknown file format","file-executable-cataloger: unable to determine ELF features: EOF","unknowns-labeler: no package identified in executable file"]},{"id":"631f0bf0d0111d8b","location":{"path":"/usr/lib/x86_64-linux-gnu/nss/libfreeblpriv3.so"},"executable":{"format":"elf","hasExports":false,"hasEntrypoint":false,"importedLibraries":[]},"unknowns":["cargo-auditable-binary-cataloger: rust cataloger: unable to read dependency information: unknown file format","file-executable-cataloger: unable to determine ELF features: EOF","unknowns-labeler: no package identified in executable file"]},{"id":"615279426cd3ea78","location":{"path":"/usr/lib/x86_64-linux-gnu/nss/libnssckbi.so"},"executable":{"format":"elf","hasExports":false,"hasEntrypoint":false,"importedLibraries":[]},"unknowns":["cargo-auditable-binary-cataloger: rust cataloger: unable to read dependency information: unknown file format","file-executable-cataloger: unable to determine ELF features: EOF","unknowns-labeler: no package identified in executable file"]},{"id":"b40decec9a3be86b","location":{"path":"/usr/lib/x86_64-linux-gnu/nss/libnssdbm3.so"},"executable":{"format":"elf","hasExports":false,"hasEntrypoint":false,"importedLibraries":[]},"unknowns":["cargo-auditable-binary-cataloger: rust cataloger: unable to read dependency information: unknown file format","file-executable-cataloger: unable to determine ELF features: EOF","unknowns-labeler: no package identified in executable file"]},{"id":"ca3405e8044a6843","location":{"path":"/usr/lib/x86_64-linux-gnu/nss/libsoftokn3.so"},"executable":{"format":"elf","hasExports":false,"hasEntrypoint":false,"importedLibraries":[]},"unknowns":["cargo-auditable-binary-cataloger: rust cataloger: unable to read dependency information: unknown file format","file-executable-cataloger: unable to determine ELF features: EOF","unknowns-labeler: no package identified in executable file"]}],"source":{"id":"4b75dea98bee6701e2195571e14501439f4da1e51469b14050511f2a5cc3a585","name":"axolotl","version":"1.6.0","type":"snap","metadata":{"summary":"A signal client.","base":"core20","grade":"stable","confinement":"strict","architectures":["amd64"],"digests":[{"algorithm":"sha256","value":"0239a156b77f0c0963629e11f08afaa644119747eedebc9b061e694f5bbba738"}]}},"distro":{},"descriptor":{"name":"syft","version":"1.26.1-SNAPSHOT-17b4bf3c","configuration":{"catalogers":{"requested":{"default":["installed","file"]},"used":["alpm-db-cataloger","apk-db-cataloger","binary-classifier-cataloger","bitnami-cataloger","cargo-auditable-binary-cataloger","conan-info-cataloger","dotnet-deps-binary-cataloger","dpkg-db-cataloger","elf-binary-package-cataloger","file-content-cataloger","file-digest-cataloger","file-executable-cataloger","file-metadata-cataloger","go-module-binary-cataloger","graalvm-native-image-cataloger","homebrew-cataloger","java-archive-cataloger","java-jvm-cataloger","javascript-package-cataloger","linux-kernel-cataloger","lua-rock-cataloger","nix-cataloger","pe-binary-package-cataloger","php-composer-installed-cataloger","php-interpreter-cataloger","portage-cataloger","python-installed-package-cataloger","r-package-cataloger","rpm-db-cataloger","ruby-installed-gemspec-cataloger"]},"data-generation":{"generate-cpes":true},"files":{"content":{"globs":null,"skip-files-above-size":0},"hashers":["sha-1","sha-256"],"selection":"owned-by-package"},"licenses":{"coverage":75,"include-content":"none"},"packages":{"binary":["python-binary","python-binary-lib","pypy-binary-lib","go-binary","julia-binary","helm","redis-binary","java-binary-openjdk","java-binary-ibm","java-binary-oracle","java-binary-graalvm","java-binary-jdk","nodejs-binary","go-binary-hint","busybox-binary","util-linux-binary","haproxy-binary","perl-binary","php-composer-binary","httpd-binary","memcached-binary","traefik-binary","arangodb-binary","postgresql-binary","mysql-binary","mysql-binary","mysql-binary","xtrabackup-binary","mariadb-binary","rust-standard-library-linux","rust-standard-library-macos","ruby-binary","erlang-binary","erlang-alpine-binary","erlang-library","swipl-binary","dart-binary","haskell-ghc-binary","haskell-cabal-binary","haskell-stack-binary","consul-binary","nginx-binary","bash-binary","openssl-binary","gcc-binary","fluent-bit-binary","wordpress-cli-binary","curl-binary","lighttpd-binary","proftpd-binary","zstd-binary","xz-binary","gzip-binary","sqlcipher-binary","jq-binary","chrome-binary"],"dotnet":{"dep-packages-must-claim-dll":true,"dep-packages-must-have-dll":false,"propagate-dll-claims-to-parents":true,"relax-dll-claims-when-bundling-detected":true},"golang":{"local-mod-cache-dir":"/home/runner/go/pkg/mod","local-vendor-dir":"","main-module-version":{"from-build-settings":true,"from-contents":false,"from-ld-flags":true},"proxies":["https://proxy.golang.org","direct"],"search-local-mod-cache-licenses":false,"search-local-vendor-licenses":false,"search-remote-licenses":false},"java-archive":{"include-indexed-archives":true,"include-unindexed-archives":false,"maven-base-url":"https://repo1.maven.org/maven2","maven-localrepository-dir":"/home/runner/.m2/repository","max-parent-recursive-depth":0,"resolve-transitive-dependencies":false,"use-maven-localrepository":false,"use-network":false},"javascript":{"include-dev-dependencies":false,"npm-base-url":"https://registry.npmjs.org","search-remote-licenses":false},"linux-kernel":{"catalog-modules":true},"nix":{"capture-owned-files":false},"python":{"guess-unpinned-requirements":false}},"relationships":{"exclude-binary-packages-with-file-ownership-overlap":true,"package-file-ownership":true,"package-file-ownership-overlap":true},"search":{"scope":"squashed"}}},"schema":{"version":"16.0.34","url":"https://raw.githubusercontent.com/anchore/syft/main/schema/json/schema-16.0.34.json"}}
