{"artifacts":[{"id":"7623570987f0be10","name":"github.com/briandowns/spinner","version":"v1.23.0","type":"go-module","foundBy":"go-module-binary-cataloger","locations":[{"path":"/bin/dns-scout","accessPath":"/bin/dns-scout","annotations":{"evidence":"primary"}}],"licenses":[],"language":"go","cpes":[{"cpe":"cpe:2.3:a:briandowns:spinner:v1.23.0:*:*:*:*:*:*:*","source":"syft-generated"}],"purl":"pkg:golang/github.com/briandowns/spinner@v1.23.0","metadataType":"go-module-buildinfo-entry","metadata":{"goCompiledVersion":"go1.21.3","architecture":"amd64","h1Digest":"h1:alDF2guRWqa/FOZZYWjlMIx2L6H0wyewPxo/CH4Pt2A=","mainModule":"github.com/careyjames/dns-scout","goCryptoSettings":["standard-crypto"]}},{"id":"388316eadba4327e","name":"github.com/careyjames/dns-scout","version":"v0.0.0-20231105182954-f5c2f6b83a81","type":"go-module","foundBy":"go-module-binary-cataloger","locations":[{"path":"/bin/dns-scout","accessPath":"/bin/dns-scout","annotations":{"evidence":"primary"}}],"licenses":[],"language":"go","cpes":[{"cpe":"cpe:2.3:a:careyjames:dns-scout:v0.0.0-20231105182954-f5c2f6b83a81:*:*:*:*:*:*:*","source":"syft-generated"},{"cpe":"cpe:2.3:a:careyjames:dns_scout:v0.0.0-20231105182954-f5c2f6b83a81:*:*:*:*:*:*:*","source":"syft-generated"}],"purl":"pkg:golang/github.com/careyjames/dns-scout@v0.0.0-20231105182954-f5c2f6b83a81","metadataType":"go-module-buildinfo-entry","metadata":{"goBuildSettings":[{"key":"-buildmode","value":"exe"},{"key":"-compiler","value":"gc"},{"key":"CGO_ENABLED","value":"1"},{"key":"CGO_CFLAGS","value":""},{"key":"CGO_CPPFLAGS","value":""},{"key":"CGO_CXXFLAGS","value":""},{"key":"CGO_LDFLAGS","value":""},{"key":"GOARCH","value":"amd64"},{"key":"GOOS","value":"linux"},{"key":"GOAMD64","value":"v1"},{"key":"vcs","value":"git"},{"key":"vcs.revision","value":"f5c2f6b83a8153f81af9be1894e12ce0531a0d93"},{"key":"vcs.time","value":"2023-11-05T18:29:54Z"},{"key":"vcs.modified","value":"true"}],"goCompiledVersion":"go1.21.3","architecture":"amd64","mainModule":"github.com/careyjames/dns-scout","goCryptoSettings":["standard-crypto"]}},{"id":"6ac595c138cacebe","name":"github.com/careyjames/dns-scout","version":"v0.0.0-20231105182954-f5c2f6b83a81","type":"go-module","foundBy":"go-module-binary-cataloger","locations":[{"path":"/bin/generate_sitemap","accessPath":"/bin/generate_sitemap","annotations":{"evidence":"primary"}}],"licenses":[],"language":"go","cpes":[{"cpe":"cpe:2.3:a:careyjames:dns-scout:v0.0.0-20231105182954-f5c2f6b83a81:*:*:*:*:*:*:*","source":"syft-generated"},{"cpe":"cpe:2.3:a:careyjames:dns_scout:v0.0.0-20231105182954-f5c2f6b83a81:*:*:*:*:*:*:*","source":"syft-generated"}],"purl":"pkg:golang/github.com/careyjames/dns-scout@v0.0.0-20231105182954-f5c2f6b83a81","metadataType":"go-module-buildinfo-entry","metadata":{"goBuildSettings":[{"key":"-buildmode","value":"exe"},{"key":"-compiler","value":"gc"},{"key":"CGO_ENABLED","value":"1"},{"key":"CGO_CFLAGS","value":""},{"key":"CGO_CPPFLAGS","value":""},{"key":"CGO_CXXFLAGS","value":""},{"key":"CGO_LDFLAGS","value":""},{"key":"GOARCH","value":"amd64"},{"key":"GOOS","value":"linux"},{"key":"GOAMD64","value":"v1"},{"key":"vcs","value":"git"},{"key":"vcs.revision","value":"f5c2f6b83a8153f81af9be1894e12ce0531a0d93"},{"key":"vcs.time","value":"2023-11-05T18:29:54Z"},{"key":"vcs.modified","value":"true"}],"goCompiledVersion":"go1.21.3","architecture":"amd64","mainModule":"github.com/careyjames/dns-scout"}},{"id":"eb8c0fa703a75c71","name":"github.com/chzyer/readline","version":"v1.5.1","type":"go-module","foundBy":"go-module-binary-cataloger","locations":[{"path":"/bin/dns-scout","accessPath":"/bin/dns-scout","annotations":{"evidence":"primary"}}],"licenses":[],"language":"go","cpes":[{"cpe":"cpe:2.3:a:chzyer:readline:v1.5.1:*:*:*:*:*:*:*","source":"syft-generated"}],"purl":"pkg:golang/github.com/chzyer/readline@v1.5.1","metadataType":"go-module-buildinfo-entry","metadata":{"goCompiledVersion":"go1.21.3","architecture":"amd64","h1Digest":"h1:upd/6fQk4src78LMRzh5vItIt361/o4uq553V8B5sGI=","mainModule":"github.com/careyjames/dns-scout","goCryptoSettings":["standard-crypto"]}},{"id":"3da322d548bf5c18","name":"github.com/fatih/color","version":"v1.15.0","type":"go-module","foundBy":"go-module-binary-cataloger","locations":[{"path":"/bin/dns-scout","accessPath":"/bin/dns-scout","annotations":{"evidence":"primary"}}],"licenses":[],"language":"go","cpes":[{"cpe":"cpe:2.3:a:fatih:color:v1.15.0:*:*:*:*:*:*:*","source":"syft-generated"}],"purl":"pkg:golang/github.com/fatih/color@v1.15.0","metadataType":"go-module-buildinfo-entry","metadata":{"goCompiledVersion":"go1.21.3","architecture":"amd64","h1Digest":"h1:kOqh6YHBtK8aywxGerMG2Eq3H6Qgoqeo13Bk2Mv/nBs=","mainModule":"github.com/careyjames/dns-scout","goCryptoSettings":["standard-crypto"]}},{"id":"8279dfef4ee3221d","name":"github.com/likexian/gokit","version":"v0.25.13","type":"go-module","foundBy":"go-module-binary-cataloger","locations":[{"path":"/bin/dns-scout","accessPath":"/bin/dns-scout","annotations":{"evidence":"primary"}}],"licenses":[],"language":"go","cpes":[{"cpe":"cpe:2.3:a:likexian:gokit:v0.25.13:*:*:*:*:*:*:*","source":"syft-generated"}],"purl":"pkg:golang/github.com/likexian/gokit@v0.25.13","metadataType":"go-module-buildinfo-entry","metadata":{"goCompiledVersion":"go1.21.3","architecture":"amd64","h1Digest":"h1:p2Uw3+6fGG53CwdU2Dz0T6bOycdb2+bAFAa3ymwWVkM=","mainModule":"github.com/careyjames/dns-scout","goCryptoSettings":["standard-crypto"]}},{"id":"8204b0a01b94553e","name":"github.com/likexian/whois","version":"v1.15.1","type":"go-module","foundBy":"go-module-binary-cataloger","locations":[{"path":"/bin/dns-scout","accessPath":"/bin/dns-scout","annotations":{"evidence":"primary"}}],"licenses":[],"language":"go","cpes":[{"cpe":"cpe:2.3:a:likexian:whois:v1.15.1:*:*:*:*:*:*:*","source":"syft-generated"}],"purl":"pkg:golang/github.com/likexian/whois@v1.15.1","metadataType":"go-module-buildinfo-entry","metadata":{"goCompiledVersion":"go1.21.3","architecture":"amd64","h1Digest":"h1:6vTMI8n9s1eJdmcO4R9h1x99aQWIZZX1CD3am68gApU=","mainModule":"github.com/careyjames/dns-scout","goCryptoSettings":["standard-crypto"]}},{"id":"4bc5206f93575217","name":"github.com/likexian/whois-parser","version":"v1.24.9","type":"go-module","foundBy":"go-module-binary-cataloger","locations":[{"path":"/bin/dns-scout","accessPath":"/bin/dns-scout","annotations":{"evidence":"primary"}}],"licenses":[],"language":"go","cpes":[{"cpe":"cpe:2.3:a:likexian:whois-parser:v1.24.9:*:*:*:*:*:*:*","source":"syft-generated"},{"cpe":"cpe:2.3:a:likexian:whois_parser:v1.24.9:*:*:*:*:*:*:*","source":"syft-generated"}],"purl":"pkg:golang/github.com/likexian/whois-parser@v1.24.9","metadataType":"go-module-buildinfo-entry","metadata":{"goCompiledVersion":"go1.21.3","architecture":"amd64","h1Digest":"h1:BT6fzO3lj3F07yzVv0YXoaj+K4Ush0/cF+Yp6tvJJgk=","mainModule":"github.com/careyjames/dns-scout","goCryptoSettings":["standard-crypto"]}},{"id":"dec973ca257e91a7","name":"github.com/mattn/go-colorable","version":"v0.1.13","type":"go-module","foundBy":"go-module-binary-cataloger","locations":[{"path":"/bin/dns-scout","accessPath":"/bin/dns-scout","annotations":{"evidence":"primary"}}],"licenses":[],"language":"go","cpes":[{"cpe":"cpe:2.3:a:mattn:go-colorable:v0.1.13:*:*:*:*:*:*:*","source":"syft-generated"},{"cpe":"cpe:2.3:a:mattn:go_colorable:v0.1.13:*:*:*:*:*:*:*","source":"syft-generated"}],"purl":"pkg:golang/github.com/mattn/go-colorable@v0.1.13","metadataType":"go-module-buildinfo-entry","metadata":{"goCompiledVersion":"go1.21.3","architecture":"amd64","h1Digest":"h1:fFA4WZxdEF4tXPZVKMLwD8oUnCTTo08duU7wxecdEvA=","mainModule":"github.com/careyjames/dns-scout","goCryptoSettings":["standard-crypto"]}},{"id":"8aeb71a15ad204cd","name":"github.com/mattn/go-isatty","version":"v0.0.19","type":"go-module","foundBy":"go-module-binary-cataloger","locations":[{"path":"/bin/dns-scout","accessPath":"/bin/dns-scout","annotations":{"evidence":"primary"}}],"licenses":[],"language":"go","cpes":[{"cpe":"cpe:2.3:a:mattn:go-isatty:v0.0.19:*:*:*:*:*:*:*","source":"syft-generated"},{"cpe":"cpe:2.3:a:mattn:go_isatty:v0.0.19:*:*:*:*:*:*:*","source":"syft-generated"}],"purl":"pkg:golang/github.com/mattn/go-isatty@v0.0.19","metadataType":"go-module-buildinfo-entry","metadata":{"goCompiledVersion":"go1.21.3","architecture":"amd64","h1Digest":"h1:JITubQf0MOLdlGRuRq+jtsDlekdYPia9ZFsB8h/APPA=","mainModule":"github.com/careyjames/dns-scout","goCryptoSettings":["standard-crypto"]}},{"id":"88a0a958459a6cc4","name":"github.com/miekg/dns","version":"v1.1.56","type":"go-module","foundBy":"go-module-binary-cataloger","locations":[{"path":"/bin/dns-scout","accessPath":"/bin/dns-scout","annotations":{"evidence":"primary"}}],"licenses":[],"language":"go","cpes":[{"cpe":"cpe:2.3:a:miekg:dns:v1.1.56:*:*:*:*:*:*:*","source":"syft-generated"}],"purl":"pkg:golang/github.com/miekg/dns@v1.1.56","metadataType":"go-module-buildinfo-entry","metadata":{"goCompiledVersion":"go1.21.3","architecture":"amd64","h1Digest":"h1:5imZaSeoRNvpM9SzWNhEcP9QliKiz20/dA2QabIGVnE=","mainModule":"github.com/careyjames/dns-scout","goCryptoSettings":["standard-crypto"]}},{"id":"213073b56588506a","name":"golang.org/x/net","version":"v0.17.0","type":"go-module","foundBy":"go-module-binary-cataloger","locations":[{"path":"/bin/dns-scout","accessPath":"/bin/dns-scout","annotations":{"evidence":"primary"}}],"licenses":[],"language":"go","cpes":[{"cpe":"cpe:2.3:a:golang:networking:v0.17.0:*:*:*:*:go:*:*","source":"nvd-cpe-dictionary"}],"purl":"pkg:golang/golang.org/x/net@v0.17.0","metadataType":"go-module-buildinfo-entry","metadata":{"goCompiledVersion":"go1.21.3","architecture":"amd64","h1Digest":"h1:pVaXccu2ozPjCXewfr1S7xza/zcXTity9cCdXQYSjIM=","mainModule":"github.com/careyjames/dns-scout","goCryptoSettings":["standard-crypto"]}},{"id":"03af38f6c00d6e13","name":"golang.org/x/sys","version":"v0.13.0","type":"go-module","foundBy":"go-module-binary-cataloger","locations":[{"path":"/bin/dns-scout","accessPath":"/bin/dns-scout","annotations":{"evidence":"primary"}}],"licenses":[],"language":"go","cpes":[{"cpe":"cpe:2.3:a:golang:x\\/sys:v0.13.0:*:*:*:*:*:*:*","source":"syft-generated"}],"purl":"pkg:golang/golang.org/x/sys@v0.13.0","metadataType":"go-module-buildinfo-entry","metadata":{"goCompiledVersion":"go1.21.3","architecture":"amd64","h1Digest":"h1:Af8nKPmuFypiUBjVoU9V20FiaFXOcuZI21p0ycVYYGE=","mainModule":"github.com/careyjames/dns-scout","goCryptoSettings":["standard-crypto"]}},{"id":"b71ba94a9f3328fa","name":"golang.org/x/term","version":"v0.13.0","type":"go-module","foundBy":"go-module-binary-cataloger","locations":[{"path":"/bin/dns-scout","accessPath":"/bin/dns-scout","annotations":{"evidence":"primary"}}],"licenses":[],"language":"go","cpes":[{"cpe":"cpe:2.3:a:golang:x\\/term:v0.13.0:*:*:*:*:*:*:*","source":"syft-generated"}],"purl":"pkg:golang/golang.org/x/term@v0.13.0","metadataType":"go-module-buildinfo-entry","metadata":{"goCompiledVersion":"go1.21.3","architecture":"amd64","h1Digest":"h1:bb+I9cTfFazGW51MZqBVmZy7+JEJMouUHTUSKVQLBek=","mainModule":"github.com/careyjames/dns-scout","goCryptoSettings":["standard-crypto"]}},{"id":"24a5832b4311adfd","name":"golang.org/x/text","version":"v0.13.0","type":"go-module","foundBy":"go-module-binary-cataloger","locations":[{"path":"/bin/dns-scout","accessPath":"/bin/dns-scout","annotations":{"evidence":"primary"}}],"licenses":[],"language":"go","cpes":[{"cpe":"cpe:2.3:a:golang:text:v0.13.0:*:*:*:*:*:*:*","source":"nvd-cpe-dictionary"}],"purl":"pkg:golang/golang.org/x/text@v0.13.0","metadataType":"go-module-buildinfo-entry","metadata":{"goCompiledVersion":"go1.21.3","architecture":"amd64","h1Digest":"h1:ablQoSUd0tRdKxZewP80B+BaqeKJuVhuRxj/dkrun3k=","mainModule":"github.com/careyjames/dns-scout","goCryptoSettings":["standard-crypto"]}},{"id":"0d013e9dcbc9da9d","name":"stdlib","version":"go1.21.3","type":"go-module","foundBy":"go-module-binary-cataloger","locations":[{"path":"/bin/dns-scout","accessPath":"/bin/dns-scout","annotations":{"evidence":"primary"}}],"licenses":[{"value":"BSD-3-Clause","spdxExpression":"BSD-3-Clause","type":"declared","urls":[],"locations":[]}],"language":"go","cpes":[{"cpe":"cpe:2.3:a:golang:go:1.21.3:-:*:*:*:*:*:*","source":"syft-generated"}],"purl":"pkg:golang/stdlib@1.21.3","metadataType":"go-module-buildinfo-entry","metadata":{"goCompiledVersion":"go1.21.3","architecture":""}},{"id":"290244cdc5d5eaa4","name":"stdlib","version":"go1.21.3","type":"go-module","foundBy":"go-module-binary-cataloger","locations":[{"path":"/bin/generate_sitemap","accessPath":"/bin/generate_sitemap","annotations":{"evidence":"primary"}}],"licenses":[{"value":"BSD-3-Clause","spdxExpression":"BSD-3-Clause","type":"declared","urls":[],"locations":[]}],"language":"go","cpes":[{"cpe":"cpe:2.3:a:golang:go:1.21.3:-:*:*:*:*:*:*","source":"syft-generated"}],"purl":"pkg:golang/stdlib@1.21.3","metadataType":"go-module-buildinfo-entry","metadata":{"goCompiledVersion":"go1.21.3","architecture":""}}],"artifactRelationships":[{"parent":"03af38f6c00d6e13","child":"388316eadba4327e","type":"dependency-of"},{"parent":"03af38f6c00d6e13","child":"afe300e63f478f7a","type":"evident-by","metadata":{"kind":"primary"}},{"parent":"0d013e9dcbc9da9d","child":"388316eadba4327e","type":"dependency-of"},{"parent":"0d013e9dcbc9da9d","child":"afe300e63f478f7a","type":"evident-by","metadata":{"kind":"primary"}},{"parent":"213073b56588506a","child":"388316eadba4327e","type":"dependency-of"},{"parent":"213073b56588506a","child":"afe300e63f478f7a","type":"evident-by","metadata":{"kind":"primary"}},{"parent":"24a5832b4311adfd","child":"388316eadba4327e","type":"dependency-of"},{"parent":"24a5832b4311adfd","child":"afe300e63f478f7a","type":"evident-by","metadata":{"kind":"primary"}},{"parent":"290244cdc5d5eaa4","child":"6ac595c138cacebe","type":"dependency-of"},{"parent":"290244cdc5d5eaa4","child":"b6c21a5e5bdd100d","type":"evident-by","metadata":{"kind":"primary"}},{"parent":"388316eadba4327e","child":"afe300e63f478f7a","type":"evident-by","metadata":{"kind":"primary"}},{"parent":"3da322d548bf5c18","child":"388316eadba4327e","type":"dependency-of"},{"parent":"3da322d548bf5c18","child":"afe300e63f478f7a","type":"evident-by","metadata":{"kind":"primary"}},{"parent":"4a1454bfd434279fc8a9ade9865d6a710b3739b0d018e4193bd9a7e9c5b3aeb4","child":"03af38f6c00d6e13","type":"contains"},{"parent":"4a1454bfd434279fc8a9ade9865d6a710b3739b0d018e4193bd9a7e9c5b3aeb4","child":"0d013e9dcbc9da9d","type":"contains"},{"parent":"4a1454bfd434279fc8a9ade9865d6a710b3739b0d018e4193bd9a7e9c5b3aeb4","child":"213073b56588506a","type":"contains"},{"parent":"4a1454bfd434279fc8a9ade9865d6a710b3739b0d018e4193bd9a7e9c5b3aeb4","child":"24a5832b4311adfd","type":"contains"},{"parent":"4a1454bfd434279fc8a9ade9865d6a710b3739b0d018e4193bd9a7e9c5b3aeb4","child":"290244cdc5d5eaa4","type":"contains"},{"parent":"4a1454bfd434279fc8a9ade9865d6a710b3739b0d018e4193bd9a7e9c5b3aeb4","child":"388316eadba4327e","type":"contains"},{"parent":"4a1454bfd434279fc8a9ade9865d6a710b3739b0d018e4193bd9a7e9c5b3aeb4","child":"3da322d548bf5c18","type":"contains"},{"parent":"4a1454bfd434279fc8a9ade9865d6a710b3739b0d018e4193bd9a7e9c5b3aeb4","child":"4bc5206f93575217","type":"contains"},{"parent":"4a1454bfd434279fc8a9ade9865d6a710b3739b0d018e4193bd9a7e9c5b3aeb4","child":"6ac595c138cacebe","type":"contains"},{"parent":"4a1454bfd434279fc8a9ade9865d6a710b3739b0d018e4193bd9a7e9c5b3aeb4","child":"7623570987f0be10","type":"contains"},{"parent":"4a1454bfd434279fc8a9ade9865d6a710b3739b0d018e4193bd9a7e9c5b3aeb4","child":"8204b0a01b94553e","type":"contains"},{"parent":"4a1454bfd434279fc8a9ade9865d6a710b3739b0d018e4193bd9a7e9c5b3aeb4","child":"8279dfef4ee3221d","type":"contains"},{"parent":"4a1454bfd434279fc8a9ade9865d6a710b3739b0d018e4193bd9a7e9c5b3aeb4","child":"88a0a958459a6cc4","type":"contains"},{"parent":"4a1454bfd434279fc8a9ade9865d6a710b3739b0d018e4193bd9a7e9c5b3aeb4","child":"8aeb71a15ad204cd","type":"contains"},{"parent":"4a1454bfd434279fc8a9ade9865d6a710b3739b0d018e4193bd9a7e9c5b3aeb4","child":"b71ba94a9f3328fa","type":"contains"},{"parent":"4a1454bfd434279fc8a9ade9865d6a710b3739b0d018e4193bd9a7e9c5b3aeb4","child":"dec973ca257e91a7","type":"contains"},{"parent":"4a1454bfd434279fc8a9ade9865d6a710b3739b0d018e4193bd9a7e9c5b3aeb4","child":"eb8c0fa703a75c71","type":"contains"},{"parent":"4bc5206f93575217","child":"388316eadba4327e","type":"dependency-of"},{"parent":"4bc5206f93575217","child":"afe300e63f478f7a","type":"evident-by","metadata":{"kind":"primary"}},{"parent":"6ac595c138cacebe","child":"b6c21a5e5bdd100d","type":"evident-by","metadata":{"kind":"primary"}},{"parent":"7623570987f0be10","child":"388316eadba4327e","type":"dependency-of"},{"parent":"7623570987f0be10","child":"afe300e63f478f7a","type":"evident-by","metadata":{"kind":"primary"}},{"parent":"8204b0a01b94553e","child":"388316eadba4327e","type":"dependency-of"},{"parent":"8204b0a01b94553e","child":"afe300e63f478f7a","type":"evident-by","metadata":{"kind":"primary"}},{"parent":"8279dfef4ee3221d","child":"388316eadba4327e","type":"dependency-of"},{"parent":"8279dfef4ee3221d","child":"afe300e63f478f7a","type":"evident-by","metadata":{"kind":"primary"}},{"parent":"88a0a958459a6cc4","child":"388316eadba4327e","type":"dependency-of"},{"parent":"88a0a958459a6cc4","child":"afe300e63f478f7a","type":"evident-by","metadata":{"kind":"primary"}},{"parent":"8aeb71a15ad204cd","child":"388316eadba4327e","type":"dependency-of"},{"parent":"8aeb71a15ad204cd","child":"afe300e63f478f7a","type":"evident-by","metadata":{"kind":"primary"}},{"parent":"b71ba94a9f3328fa","child":"388316eadba4327e","type":"dependency-of"},{"parent":"b71ba94a9f3328fa","child":"afe300e63f478f7a","type":"evident-by","metadata":{"kind":"primary"}},{"parent":"dec973ca257e91a7","child":"388316eadba4327e","type":"dependency-of"},{"parent":"dec973ca257e91a7","child":"afe300e63f478f7a","type":"evident-by","metadata":{"kind":"primary"}},{"parent":"eb8c0fa703a75c71","child":"388316eadba4327e","type":"dependency-of"},{"parent":"eb8c0fa703a75c71","child":"afe300e63f478f7a","type":"evident-by","metadata":{"kind":"primary"}}],"files":[{"id":"afe300e63f478f7a","location":{"path":"/bin/dns-scout"},"metadata":{"mode":755,"type":"RegularFile","userID":0,"groupID":0,"mimeType":"application/x-executable","size":9284699},"digests":[{"algorithm":"sha1","value":"e71f26bced7f7bcc694ad747d4cf1ea012097ef2"},{"algorithm":"sha256","value":"24e40e1b09651134c867fc7ee2c16fd01d82b3257972236fd74e2ea671cf8280"}],"executable":{"format":"elf","hasExports":true,"hasEntrypoint":true,"importedLibraries":["libc.so.6"],"elfSecurityFeatures":{"symbolTableStripped":false,"stackCanary":false,"nx":true,"relRO":"none","pie":false,"dso":false,"safeStack":false,"cfi":false,"fortify":false}}},{"id":"b6c21a5e5bdd100d","location":{"path":"/bin/generate_sitemap"},"metadata":{"mode":755,"type":"RegularFile","userID":0,"groupID":0,"mimeType":"application/x-executable","size":2091530},"digests":[{"algorithm":"sha1","value":"3e774cb2791c1eea5f00eb9dd4a4971bbe0e195f"},{"algorithm":"sha256","value":"4ba9932fcb780985c6014d79b02af61d9bd2fb0303ea47a8d3e748d9591198e3"}],"executable":{"format":"elf","hasExports":false,"hasEntrypoint":true,"importedLibraries":[],"elfSecurityFeatures":{"symbolTableStripped":false,"nx":true,"relRO":"none","pie":false,"dso":false,"cfi":false,"fortify":false}}}],"source":{"id":"4a1454bfd434279fc8a9ade9865d6a710b3739b0d018e4193bd9a7e9c5b3aeb4","name":"dns-scout","version":"6.20","type":"snap","metadata":{"summary":"DNS Scout for Linux/MacOS","base":"core22","grade":"stable","confinement":"strict","architectures":["amd64"],"digests":[{"algorithm":"sha256","value":"30d944cce07e829480b13b6e6f63d6f9e231951f8240ae9f0fa4fb4a311d9f55"}]}},"distro":{},"descriptor":{"name":"syft","version":"1.26.1-SNAPSHOT-17b4bf3c","configuration":{"catalogers":{"requested":{"default":["installed","file"]},"used":["alpm-db-cataloger","apk-db-cataloger","binary-classifier-cataloger","bitnami-cataloger","cargo-auditable-binary-cataloger","conan-info-cataloger","dotnet-deps-binary-cataloger","dpkg-db-cataloger","elf-binary-package-cataloger","file-content-cataloger","file-digest-cataloger","file-executable-cataloger","file-metadata-cataloger","go-module-binary-cataloger","graalvm-native-image-cataloger","homebrew-cataloger","java-archive-cataloger","java-jvm-cataloger","javascript-package-cataloger","linux-kernel-cataloger","lua-rock-cataloger","nix-cataloger","pe-binary-package-cataloger","php-composer-installed-cataloger","php-interpreter-cataloger","portage-cataloger","python-installed-package-cataloger","r-package-cataloger","rpm-db-cataloger","ruby-installed-gemspec-cataloger"]},"data-generation":{"generate-cpes":true},"files":{"content":{"globs":null,"skip-files-above-size":0},"hashers":["sha-1","sha-256"],"selection":"owned-by-package"},"licenses":{"coverage":75,"include-content":"none"},"packages":{"binary":["python-binary","python-binary-lib","pypy-binary-lib","go-binary","julia-binary","helm","redis-binary","java-binary-openjdk","java-binary-ibm","java-binary-oracle","java-binary-graalvm","java-binary-jdk","nodejs-binary","go-binary-hint","busybox-binary","util-linux-binary","haproxy-binary","perl-binary","php-composer-binary","httpd-binary","memcached-binary","traefik-binary","arangodb-binary","postgresql-binary","mysql-binary","mysql-binary","mysql-binary","xtrabackup-binary","mariadb-binary","rust-standard-library-linux","rust-standard-library-macos","ruby-binary","erlang-binary","erlang-alpine-binary","erlang-library","swipl-binary","dart-binary","haskell-ghc-binary","haskell-cabal-binary","haskell-stack-binary","consul-binary","nginx-binary","bash-binary","openssl-binary","gcc-binary","fluent-bit-binary","wordpress-cli-binary","curl-binary","lighttpd-binary","proftpd-binary","zstd-binary","xz-binary","gzip-binary","sqlcipher-binary","jq-binary","chrome-binary"],"dotnet":{"dep-packages-must-claim-dll":true,"dep-packages-must-have-dll":false,"propagate-dll-claims-to-parents":true,"relax-dll-claims-when-bundling-detected":true},"golang":{"local-mod-cache-dir":"/home/runner/go/pkg/mod","local-vendor-dir":"","main-module-version":{"from-build-settings":true,"from-contents":false,"from-ld-flags":true},"proxies":["https://proxy.golang.org","direct"],"search-local-mod-cache-licenses":false,"search-local-vendor-licenses":false,"search-remote-licenses":false},"java-archive":{"include-indexed-archives":true,"include-unindexed-archives":false,"maven-base-url":"https://repo1.maven.org/maven2","maven-localrepository-dir":"/home/runner/.m2/repository","max-parent-recursive-depth":0,"resolve-transitive-dependencies":false,"use-maven-localrepository":false,"use-network":false},"javascript":{"include-dev-dependencies":false,"npm-base-url":"https://registry.npmjs.org","search-remote-licenses":false},"linux-kernel":{"catalog-modules":true},"nix":{"capture-owned-files":false},"python":{"guess-unpinned-requirements":false}},"relationships":{"exclude-binary-packages-with-file-ownership-overlap":true,"package-file-ownership":true,"package-file-ownership-overlap":true},"search":{"scope":"squashed"}}},"schema":{"version":"16.0.34","url":"https://raw.githubusercontent.com/anchore/syft/main/schema/json/schema-16.0.34.json"}}
