{"artifacts":[{"id":"5e557fbe1fd5aa47","name":"Jankson-Fabric","version":"4.0.0+j1.2.0","type":"java-archive","foundBy":"java-archive-cataloger","locations":[{"path":"/test/data/RPMTW-Update-Mod-Fabric-1.18.1-1.3.1.jar","accessPath":"/test/data/RPMTW-Update-Mod-Fabric-1.18.1-1.3.1.jar:META-INF/jars/LibGui-5.3.1+1.18.jar:META-INF/jars/Jankson-Fabric-4.0.0+j1.2.0.jar","annotations":{"evidence":"primary"}}],"licenses":[],"language":"java","cpes":[{"cpe":"cpe:2.3:a:Jankson-Fabric:Jankson-Fabric:4.0.0\\+j1.2.0:*:*:*:*:*:*:*","source":"syft-generated"},{"cpe":"cpe:2.3:a:Jankson-Fabric:Jankson_Fabric:4.0.0\\+j1.2.0:*:*:*:*:*:*:*","source":"syft-generated"},{"cpe":"cpe:2.3:a:Jankson_Fabric:Jankson-Fabric:4.0.0\\+j1.2.0:*:*:*:*:*:*:*","source":"syft-generated"},{"cpe":"cpe:2.3:a:Jankson_Fabric:Jankson_Fabric:4.0.0\\+j1.2.0:*:*:*:*:*:*:*","source":"syft-generated"},{"cpe":"cpe:2.3:a:Jankson:Jankson-Fabric:4.0.0\\+j1.2.0:*:*:*:*:*:*:*","source":"syft-generated"},{"cpe":"cpe:2.3:a:Jankson:Jankson_Fabric:4.0.0\\+j1.2.0:*:*:*:*:*:*:*","source":"syft-generated"}],"purl":"pkg:maven/Jankson-Fabric/Jankson-Fabric@4.0.0%2Bj1.2.0","metadataType":"java-archive","metadata":{"virtualPath":"/test/data/RPMTW-Update-Mod-Fabric-1.18.1-1.3.1.jar:META-INF/jars/LibGui-5.3.1+1.18.jar:META-INF/jars/Jankson-Fabric-4.0.0+j1.2.0.jar","manifest":{"main":[{"key":"Manifest-Version","value":"1.0"},{"key":"Fabric-Gradle-Version","value":"7.2"},{"key":"Fabric-Loom-Version","value":"0.10.55"},{"key":"Fabric-Mixin-Compile-Extensions-Version","value":"0.4.6"},{"key":"Fabric-Minecraft-Version","value":"1.18-pre1"},{"key":"Fabric-Tiny-Remapper-Version","value":"0.7.0"},{"key":"Fabric-Loader-Version","value":"0.12.5"},{"key":"Fabric-Mixin-Version","value":"0.10.6+mixin.0.8.4"},{"key":"Fabric-Mixin-Group","value":"net.fabricmc"},{"key":"Fabric-Mapping-Namespace","value":"intermediary"}]},"digest":[{"algorithm":"sha1","value":"3ff1fdf54d4e29f81f1e1404940aa05b9a1f86d7"}]}},{"id":"f2a933110e480460","name":"LibGui","version":"5.3.1+1.18","type":"java-archive","foundBy":"java-archive-cataloger","locations":[{"path":"/test/data/RPMTW-Update-Mod-Fabric-1.18.1-1.3.1.jar","accessPath":"/test/data/RPMTW-Update-Mod-Fabric-1.18.1-1.3.1.jar:META-INF/jars/LibGui-5.3.1+1.18.jar","annotations":{"evidence":"primary"}}],"licenses":[{"value":"MIT","spdxExpression":"MIT","type":"concluded","urls":[],"locations":[{"path":"/test/data/RPMTW-Update-Mod-Fabric-1.18.1-1.3.1.jar","accessPath":"/test/data/RPMTW-Update-Mod-Fabric-1.18.1-1.3.1.jar:META-INF/jars/LibGui-5.3.1+1.18.jar","annotations":{"evidence":"primary"}}]}],"language":"java","cpes":[{"cpe":"cpe:2.3:a:LibGui:LibGui:5.3.1\\+1.18:*:*:*:*:*:*:*","source":"syft-generated"}],"purl":"pkg:maven/LibGui/LibGui@5.3.1%2B1.18","metadataType":"java-archive","metadata":{"virtualPath":"/test/data/RPMTW-Update-Mod-Fabric-1.18.1-1.3.1.jar:META-INF/jars/LibGui-5.3.1+1.18.jar","manifest":{"main":[{"key":"Manifest-Version","value":"1.0"},{"key":"Fabric-Gradle-Version","value":"7.2"},{"key":"Fabric-Loom-Version","value":"0.10.66"},{"key":"Fabric-Mixin-Compile-Extensions-Version","value":"0.4.6"},{"key":"Fabric-Minecraft-Version","value":"1.18"},{"key":"Fabric-Tiny-Remapper-Version","value":"0.7.0"},{"key":"Fabric-Loader-Version","value":"0.12.8"},{"key":"Fabric-Mixin-Version","value":"0.10.7+mixin.0.8.4"},{"key":"Fabric-Mixin-Group","value":"net.fabricmc"},{"key":"Fabric-Mapping-Namespace","value":"intermediary"}]},"digest":[{"algorithm":"sha1","value":"dbebce96c8259f5e159760f75a3f720c0ddf913b"}]}},{"id":"76ddf373afcb14e6","name":"RPMTW-Update-Mod-Fabric","version":"1.18.1-1.3.1","type":"java-archive","foundBy":"java-archive-cataloger","locations":[{"path":"/test/data/RPMTW-Update-Mod-Fabric-1.18.1-1.3.1.jar","accessPath":"/test/data/RPMTW-Update-Mod-Fabric-1.18.1-1.3.1.jar","annotations":{"evidence":"primary"}}],"licenses":[],"language":"java","cpes":[{"cpe":"cpe:2.3:a:RPMTW-Update-Mod-Fabric:RPMTW-Update-Mod-Fabric:1.18.1-1.3.1:*:*:*:*:*:*:*","source":"syft-generated"},{"cpe":"cpe:2.3:a:RPMTW-Update-Mod-Fabric:RPMTW_Update_Mod_Fabric:1.18.1-1.3.1:*:*:*:*:*:*:*","source":"syft-generated"},{"cpe":"cpe:2.3:a:RPMTW_Update_Mod_Fabric:RPMTW-Update-Mod-Fabric:1.18.1-1.3.1:*:*:*:*:*:*:*","source":"syft-generated"},{"cpe":"cpe:2.3:a:RPMTW_Update_Mod_Fabric:RPMTW_Update_Mod_Fabric:1.18.1-1.3.1:*:*:*:*:*:*:*","source":"syft-generated"},{"cpe":"cpe:2.3:a:RPMTW-Update-Mod:RPMTW-Update-Mod-Fabric:1.18.1-1.3.1:*:*:*:*:*:*:*","source":"syft-generated"},{"cpe":"cpe:2.3:a:RPMTW-Update-Mod:RPMTW_Update_Mod_Fabric:1.18.1-1.3.1:*:*:*:*:*:*:*","source":"syft-generated"},{"cpe":"cpe:2.3:a:RPMTW_Update_Mod:RPMTW-Update-Mod-Fabric:1.18.1-1.3.1:*:*:*:*:*:*:*","source":"syft-generated"},{"cpe":"cpe:2.3:a:RPMTW_Update_Mod:RPMTW_Update_Mod_Fabric:1.18.1-1.3.1:*:*:*:*:*:*:*","source":"syft-generated"},{"cpe":"cpe:2.3:a:RPMTW-Update:RPMTW-Update-Mod-Fabric:1.18.1-1.3.1:*:*:*:*:*:*:*","source":"syft-generated"},{"cpe":"cpe:2.3:a:RPMTW-Update:RPMTW_Update_Mod_Fabric:1.18.1-1.3.1:*:*:*:*:*:*:*","source":"syft-generated"},{"cpe":"cpe:2.3:a:RPMTW_Update:RPMTW-Update-Mod-Fabric:1.18.1-1.3.1:*:*:*:*:*:*:*","source":"syft-generated"},{"cpe":"cpe:2.3:a:RPMTW_Update:RPMTW_Update_Mod_Fabric:1.18.1-1.3.1:*:*:*:*:*:*:*","source":"syft-generated"},{"cpe":"cpe:2.3:a:RPMTW:RPMTW-Update-Mod-Fabric:1.18.1-1.3.1:*:*:*:*:*:*:*","source":"syft-generated"},{"cpe":"cpe:2.3:a:RPMTW:RPMTW_Update_Mod_Fabric:1.18.1-1.3.1:*:*:*:*:*:*:*","source":"syft-generated"}],"purl":"pkg:maven/RPMTW-Update-Mod-Fabric/RPMTW-Update-Mod-Fabric@1.18.1-1.3.1","metadataType":"java-archive","metadata":{"virtualPath":"/test/data/RPMTW-Update-Mod-Fabric-1.18.1-1.3.1.jar","manifest":{"main":[{"key":"Manifest-Version","value":"1.0"},{"key":"Fabric-Gradle-Version","value":"7.3"},{"key":"Fabric-Loom-Version","value":"0.10.66"},{"key":"Fabric-Mixin-Compile-Extensions-Version","value":"0.4.6"},{"key":"Fabric-Minecraft-Version","value":"1.18.2"},{"key":"Fabric-Tiny-Remapper-Version","value":"0.7.0"},{"key":"Fabric-Loader-Version","value":"0.13.3"},{"key":"Fabric-Mixin-Version","value":"0.11.2+mixin.0.8.5"},{"key":"Fabric-Mixin-Group","value":"net.fabricmc"},{"key":"Fabric-Mapping-Namespace","value":"intermediary"}]},"digest":[{"algorithm":"sha1","value":"e2e19d6cd5a453b6417d85208b12742d4000fa39"}]}},{"id":"db3c1e8e251c4c2c","name":"basic-math","version":"0.6.0","type":"java-archive","foundBy":"java-archive-cataloger","locations":[{"path":"/test/data/RPMTW-Update-Mod-Fabric-1.18.1-1.3.1.jar","accessPath":"/test/data/RPMTW-Update-Mod-Fabric-1.18.1-1.3.1.jar:META-INF/jars/cloth-config-fabric-6.1.48.jar:META-INF/jars/basic-math-0.6.0.jar","annotations":{"evidence":"primary"}}],"licenses":[],"language":"java","cpes":[{"cpe":"cpe:2.3:a:basic-math:basic-math:0.6.0:*:*:*:*:*:*:*","source":"syft-generated"},{"cpe":"cpe:2.3:a:basic-math:basic_math:0.6.0:*:*:*:*:*:*:*","source":"syft-generated"},{"cpe":"cpe:2.3:a:basic_math:basic-math:0.6.0:*:*:*:*:*:*:*","source":"syft-generated"},{"cpe":"cpe:2.3:a:basic_math:basic_math:0.6.0:*:*:*:*:*:*:*","source":"syft-generated"},{"cpe":"cpe:2.3:a:basic:basic-math:0.6.0:*:*:*:*:*:*:*","source":"syft-generated"},{"cpe":"cpe:2.3:a:basic:basic_math:0.6.0:*:*:*:*:*:*:*","source":"syft-generated"}],"purl":"pkg:maven/basic-math/basic-math@0.6.0","metadataType":"java-archive","metadata":{"virtualPath":"/test/data/RPMTW-Update-Mod-Fabric-1.18.1-1.3.1.jar:META-INF/jars/cloth-config-fabric-6.1.48.jar:META-INF/jars/basic-math-0.6.0.jar","manifest":{"main":[{"key":"Manifest-Version","value":"1.0"}]},"digest":[{"algorithm":"sha1","value":"bcf71444d5a11d1ff0b70ded97c533ece0cea489"}]}},{"id":"67b8e39e8d72c83b","name":"cloth-config-fabric","version":"6.1.48","type":"java-archive","foundBy":"java-archive-cataloger","locations":[{"path":"/test/data/RPMTW-Update-Mod-Fabric-1.18.1-1.3.1.jar","accessPath":"/test/data/RPMTW-Update-Mod-Fabric-1.18.1-1.3.1.jar:META-INF/jars/cloth-config-fabric-6.1.48.jar","annotations":{"evidence":"primary"}}],"licenses":[],"language":"java","cpes":[{"cpe":"cpe:2.3:a:cloth-config-fabric:cloth-config-fabric:6.1.48:*:*:*:*:*:*:*","source":"syft-generated"},{"cpe":"cpe:2.3:a:cloth-config-fabric:cloth_config_fabric:6.1.48:*:*:*:*:*:*:*","source":"syft-generated"},{"cpe":"cpe:2.3:a:cloth_config_fabric:cloth-config-fabric:6.1.48:*:*:*:*:*:*:*","source":"syft-generated"},{"cpe":"cpe:2.3:a:cloth_config_fabric:cloth_config_fabric:6.1.48:*:*:*:*:*:*:*","source":"syft-generated"},{"cpe":"cpe:2.3:a:cloth-config:cloth-config-fabric:6.1.48:*:*:*:*:*:*:*","source":"syft-generated"},{"cpe":"cpe:2.3:a:cloth-config:cloth_config_fabric:6.1.48:*:*:*:*:*:*:*","source":"syft-generated"},{"cpe":"cpe:2.3:a:cloth_config:cloth-config-fabric:6.1.48:*:*:*:*:*:*:*","source":"syft-generated"},{"cpe":"cpe:2.3:a:cloth_config:cloth_config_fabric:6.1.48:*:*:*:*:*:*:*","source":"syft-generated"},{"cpe":"cpe:2.3:a:cloth:cloth-config-fabric:6.1.48:*:*:*:*:*:*:*","source":"syft-generated"},{"cpe":"cpe:2.3:a:cloth:cloth_config_fabric:6.1.48:*:*:*:*:*:*:*","source":"syft-generated"}],"purl":"pkg:maven/cloth-config-fabric/cloth-config-fabric@6.1.48","metadataType":"java-archive","metadata":{"virtualPath":"/test/data/RPMTW-Update-Mod-Fabric-1.18.1-1.3.1.jar:META-INF/jars/cloth-config-fabric-6.1.48.jar","manifest":{"main":[{"key":"Manifest-Version","value":"1.0"},{"key":"Fabric-Gradle-Version","value":"7.3.1"},{"key":"Fabric-Loom-Version","value":"0.10.0.209"},{"key":"Fabric-Mixin-Compile-Extensions-Version","value":"0.4.6"},{"key":"Fabric-Minecraft-Version","value":"1.18"},{"key":"Fabric-Tiny-Remapper-Version","value":"task ':jar' property 'archiveVersion'"},{"key":"Fabric-Loader-Version","value":"0.12.5"},{"key":"Fabric-Mixin-Version","value":"0.10.6+mixin.0.8.4"},{"key":"Fabric-Mixin-Group","value":"net.fabricmc"},{"key":"Fabric-Mapping-Namespace","value":"intermediary"}]},"digest":[{"algorithm":"sha1","value":"c60956513db9fbb068bcc2bc439479b0e786f341"}]}},{"id":"6592f001d39c2e5f","name":"discord-rpc","version":"UNKNOWN","type":"binary","foundBy":"pe-binary-package-cataloger","locations":[{"path":"/bin/data/flutter_assets/packages/dart_discord_rpc/ffi-bin/discord-rpc.dll","accessPath":"/bin/data/flutter_assets/packages/dart_discord_rpc/ffi-bin/discord-rpc.dll","annotations":{"evidence":"primary"}}],"licenses":[],"language":"","cpes":[{"cpe":"cpe:2.3:a:discord-rpc:discord-rpc:*:*:*:*:*:*:*:*","source":"syft-generated"},{"cpe":"cpe:2.3:a:discord-rpc:discord_rpc:*:*:*:*:*:*:*:*","source":"syft-generated"},{"cpe":"cpe:2.3:a:discord_rpc:discord-rpc:*:*:*:*:*:*:*:*","source":"syft-generated"},{"cpe":"cpe:2.3:a:discord_rpc:discord_rpc:*:*:*:*:*:*:*:*","source":"syft-generated"},{"cpe":"cpe:2.3:a:discord:discord-rpc:*:*:*:*:*:*:*:*","source":"syft-generated"},{"cpe":"cpe:2.3:a:discord:discord_rpc:*:*:*:*:*:*:*:*","source":"syft-generated"}],"purl":"","metadataType":"pe-binary","metadata":{"VersionResources":null}},{"id":"8b055904f3477773","name":"engine.io-client","version":"2.0.0","type":"java-archive","foundBy":"java-archive-cataloger","locations":[{"path":"/test/data/RPMTW-Update-Mod-Fabric-1.18.1-1.3.1.jar","accessPath":"/test/data/RPMTW-Update-Mod-Fabric-1.18.1-1.3.1.jar:META-INF/jars/engine.io-client-2.0.0.jar","annotations":{"evidence":"primary"}}],"licenses":[{"value":"The MIT License (MIT)","spdxExpression":"","type":"declared","urls":["http://opensource.org/licenses/mit-license"],"locations":[{"path":"/test/data/RPMTW-Update-Mod-Fabric-1.18.1-1.3.1.jar","accessPath":"/test/data/RPMTW-Update-Mod-Fabric-1.18.1-1.3.1.jar:META-INF/jars/engine.io-client-2.0.0.jar","annotations":{"evidence":"primary"}}]}],"language":"java","cpes":[{"cpe":"cpe:2.3:a:engine.io-client:engine.io-client:2.0.0:*:*:*:*:*:*:*","source":"syft-generated"},{"cpe":"cpe:2.3:a:engine.io-client:engine.io_client:2.0.0:*:*:*:*:*:*:*","source":"syft-generated"},{"cpe":"cpe:2.3:a:engine.io_client:engine.io-client:2.0.0:*:*:*:*:*:*:*","source":"syft-generated"},{"cpe":"cpe:2.3:a:engine.io_client:engine.io_client:2.0.0:*:*:*:*:*:*:*","source":"syft-generated"},{"cpe":"cpe:2.3:a:engine.io:engine.io-client:2.0.0:*:*:*:*:*:*:*","source":"syft-generated"},{"cpe":"cpe:2.3:a:engine.io:engine.io_client:2.0.0:*:*:*:*:*:*:*","source":"syft-generated"},{"cpe":"cpe:2.3:a:io.socket:engine.io-client:2.0.0:*:*:*:*:*:*:*","source":"syft-generated"},{"cpe":"cpe:2.3:a:io.socket:engine.io_client:2.0.0:*:*:*:*:*:*:*","source":"syft-generated"},{"cpe":"cpe:2.3:a:socket:engine.io-client:2.0.0:*:*:*:*:*:*:*","source":"syft-generated"},{"cpe":"cpe:2.3:a:socket:engine.io_client:2.0.0:*:*:*:*:*:*:*","source":"syft-generated"}],"purl":"pkg:maven/io.socket/engine.io-client@2.0.0","metadataType":"java-archive","metadata":{"virtualPath":"/test/data/RPMTW-Update-Mod-Fabric-1.18.1-1.3.1.jar:META-INF/jars/engine.io-client-2.0.0.jar","manifest":{"main":[{"key":"Manifest-Version","value":"1.0"},{"key":"Archiver-Version","value":"Plexus Archiver"},{"key":"Built-By","value":"damien"},{"key":"Created-By","value":"Apache Maven 3.6.0"},{"key":"Build-Jdk","value":"1.8.0_275"}]},"pomProperties":{"path":"META-INF/maven/io.socket/engine.io-client/pom.properties","name":"","groupId":"io.socket","artifactId":"engine.io-client","version":"2.0.0"},"digest":[{"algorithm":"sha1","value":"58a3af80d0272b4ebc7cd0b9f01b3fb7d849c5e1"}]}},{"id":"a8c63bf4c2aa6af6","name":"fabric-language-kotlin","version":"1.7.0+kotlin.1.6.0","type":"java-archive","foundBy":"java-archive-cataloger","locations":[{"path":"/test/data/RPMTW-Update-Mod-Fabric-1.18.1-1.3.1.jar","accessPath":"/test/data/RPMTW-Update-Mod-Fabric-1.18.1-1.3.1.jar:META-INF/jars/fabric-language-kotlin-1.7.0+kotlin.1.6.0.jar","annotations":{"evidence":"primary"}}],"licenses":[],"language":"java","cpes":[{"cpe":"cpe:2.3:a:fabric-language-kotlin:fabric-language-kotlin:1.7.0\\+kotlin.1.6.0:*:*:*:*:*:*:*","source":"syft-generated"},{"cpe":"cpe:2.3:a:fabric-language-kotlin:fabric_language_kotlin:1.7.0\\+kotlin.1.6.0:*:*:*:*:*:*:*","source":"syft-generated"},{"cpe":"cpe:2.3:a:fabric_language_kotlin:fabric-language-kotlin:1.7.0\\+kotlin.1.6.0:*:*:*:*:*:*:*","source":"syft-generated"},{"cpe":"cpe:2.3:a:fabric_language_kotlin:fabric_language_kotlin:1.7.0\\+kotlin.1.6.0:*:*:*:*:*:*:*","source":"syft-generated"},{"cpe":"cpe:2.3:a:fabric-language:fabric-language-kotlin:1.7.0\\+kotlin.1.6.0:*:*:*:*:*:*:*","source":"syft-generated"},{"cpe":"cpe:2.3:a:fabric-language:fabric_language_kotlin:1.7.0\\+kotlin.1.6.0:*:*:*:*:*:*:*","source":"syft-generated"},{"cpe":"cpe:2.3:a:fabric_language:fabric-language-kotlin:1.7.0\\+kotlin.1.6.0:*:*:*:*:*:*:*","source":"syft-generated"},{"cpe":"cpe:2.3:a:fabric_language:fabric_language_kotlin:1.7.0\\+kotlin.1.6.0:*:*:*:*:*:*:*","source":"syft-generated"},{"cpe":"cpe:2.3:a:fabric:fabric-language-kotlin:1.7.0\\+kotlin.1.6.0:*:*:*:*:*:*:*","source":"syft-generated"},{"cpe":"cpe:2.3:a:fabric:fabric_language_kotlin:1.7.0\\+kotlin.1.6.0:*:*:*:*:*:*:*","source":"syft-generated"}],"purl":"pkg:maven/fabric-language-kotlin/fabric-language-kotlin@1.7.0%2Bkotlin.1.6.0","metadataType":"java-archive","metadata":{"virtualPath":"/test/data/RPMTW-Update-Mod-Fabric-1.18.1-1.3.1.jar:META-INF/jars/fabric-language-kotlin-1.7.0+kotlin.1.6.0.jar","manifest":{"main":[{"key":"Manifest-Version","value":"1.0"}]},"digest":[{"algorithm":"sha1","value":"34922d4944b47849e7eb23cbad92709e2f9750b5"}]}},{"id":"f4d28eaf236a9002","name":"jankson","version":"1.2.1","type":"java-archive","foundBy":"java-archive-cataloger","locations":[{"path":"/test/data/RPMTW-Update-Mod-Fabric-1.18.1-1.3.1.jar","accessPath":"/test/data/RPMTW-Update-Mod-Fabric-1.18.1-1.3.1.jar:META-INF/jars/LibGui-5.3.1+1.18.jar:META-INF/jars/Jankson-Fabric-4.0.0+j1.2.0.jar:META-INF/jars/jankson-1.2.1.jar","annotations":{"evidence":"primary"}}],"licenses":[],"language":"java","cpes":[{"cpe":"cpe:2.3:a:jankson:jankson:1.2.1:*:*:*:*:*:*:*","source":"syft-generated"}],"purl":"pkg:maven/jankson/jankson@1.2.1","metadataType":"java-archive","metadata":{"virtualPath":"/test/data/RPMTW-Update-Mod-Fabric-1.18.1-1.3.1.jar:META-INF/jars/LibGui-5.3.1+1.18.jar:META-INF/jars/Jankson-Fabric-4.0.0+j1.2.0.jar:META-INF/jars/jankson-1.2.1.jar","manifest":{"main":[{"key":"Manifest-Version","value":"1.0"}]},"digest":[{"algorithm":"sha1","value":"675bbec9f8d70cc5d5d565a67ec39b3e0fa45774"}]}},{"id":"7fc119acc1ec15a7","name":"json","version":"20210307","type":"java-archive","foundBy":"java-archive-cataloger","locations":[{"path":"/test/data/RPMTW-Update-Mod-Fabric-1.18.1-1.3.1.jar","accessPath":"/test/data/RPMTW-Update-Mod-Fabric-1.18.1-1.3.1.jar:META-INF/jars/json-20210307.jar","annotations":{"evidence":"primary"}}],"licenses":[{"value":"http://json.org/license.html","spdxExpression":"","type":"declared","urls":[],"locations":[{"path":"/test/data/RPMTW-Update-Mod-Fabric-1.18.1-1.3.1.jar","accessPath":"/test/data/RPMTW-Update-Mod-Fabric-1.18.1-1.3.1.jar:META-INF/jars/json-20210307.jar","annotations":{"evidence":"primary"}}]}],"language":"java","cpes":[{"cpe":"cpe:2.3:a:org.json:json:20210307:*:*:*:*:*:*:*","source":"syft-generated"},{"cpe":"cpe:2.3:a:json:json:20210307:*:*:*:*:*:*:*","source":"syft-generated"}],"purl":"pkg:maven/org.json/json@20210307","metadataType":"java-archive","metadata":{"virtualPath":"/test/data/RPMTW-Update-Mod-Fabric-1.18.1-1.3.1.jar:META-INF/jars/json-20210307.jar","manifest":{"main":[{"key":"Manifest-Version","value":"1.0"},{"key":"Automatic-Module-Name","value":"org.json"},{"key":"Bnd-LastModified","value":"1615175712577"},{"key":"Build-Jdk","value":"1.8.0_05"},{"key":"Built-By","value":"stlea_000"},{"key":"Bundle-Description","value":"JSON is a light-weight, language independent, data interchange format.        See http://www.JSON.org/        The files inthis package implement JSON encoders/decoders in Java.        It also includes the capability to convert between JSON and XML, HTTP        headers, Cookies, and CDL.        This is a reference implementation. There is a large number of JSON packages        in Java. Perhaps someday the Java community will standardize on one. Until        then, choose carefully.        The license includes this restriction: \"The software shall be used for good,        not evil.\" If your conscience cannot live with that, then choose a different        package."},{"key":"Bundle-License","value":"http://json.org/license.html"},{"key":"Bundle-ManifestVersion","value":"2"},{"key":"Bundle-Name","value":"JSON in Java"},{"key":"Bundle-SymbolicName","value":"json"},{"key":"Bundle-Version","value":"20210307.0.0"},{"key":"Created-By","value":"Apache Maven Bundle Plugin"},{"key":"Export-Package","value":"org.json;version=\"20210307.0.0\""},{"key":"Require-Capability","value":"osgi.ee;filter:=\"(&(osgi.ee=JavaSE)(version=1.6))\""},{"key":"Tool","value":"Bnd-3.0.0.201509101326"}]},"pomProperties":{"path":"META-INF/maven/org.json/json/pom.properties","name":"","groupId":"org.json","artifactId":"json","version":"20210307"},"digest":[{"algorithm":"sha1","value":"d4d1995b55f367f4e1326b46a93a7e1fbf1e80ea"}]}},{"id":"5b9df2c05182116f","name":"kotlin-reflect","version":"1.6.0","type":"java-archive","foundBy":"java-archive-cataloger","locations":[{"path":"/test/data/RPMTW-Update-Mod-Fabric-1.18.1-1.3.1.jar","accessPath":"/test/data/RPMTW-Update-Mod-Fabric-1.18.1-1.3.1.jar:META-INF/jars/fabric-language-kotlin-1.7.0+kotlin.1.6.0.jar:META-INF/jars/kotlin-reflect-1.6.0.jar","annotations":{"evidence":"primary"}}],"licenses":[],"language":"java","cpes":[{"cpe":"cpe:2.3:a:kotlin-reflect:kotlin-reflect:1.6.0:*:*:*:*:*:*:*","source":"syft-generated"},{"cpe":"cpe:2.3:a:kotlin-reflect:kotlin_reflect:1.6.0:*:*:*:*:*:*:*","source":"syft-generated"},{"cpe":"cpe:2.3:a:kotlin_reflect:kotlin-reflect:1.6.0:*:*:*:*:*:*:*","source":"syft-generated"},{"cpe":"cpe:2.3:a:kotlin_reflect:kotlin_reflect:1.6.0:*:*:*:*:*:*:*","source":"syft-generated"},{"cpe":"cpe:2.3:a:jetbrains:kotlin-reflect:1.6.0:*:*:*:*:*:*:*","source":"syft-generated"},{"cpe":"cpe:2.3:a:jetbrains:kotlin_reflect:1.6.0:*:*:*:*:*:*:*","source":"syft-generated"},{"cpe":"cpe:2.3:a:kotlin:kotlin-reflect:1.6.0:*:*:*:*:*:*:*","source":"syft-generated"},{"cpe":"cpe:2.3:a:kotlin:kotlin_reflect:1.6.0:*:*:*:*:*:*:*","source":"syft-generated"}],"purl":"pkg:maven/kotlin-reflect/kotlin-reflect@1.6.0","metadataType":"java-archive","metadata":{"virtualPath":"/test/data/RPMTW-Update-Mod-Fabric-1.18.1-1.3.1.jar:META-INF/jars/fabric-language-kotlin-1.7.0+kotlin.1.6.0.jar:META-INF/jars/kotlin-reflect-1.6.0.jar","manifest":{"main":[{"key":"Manifest-Version","value":"1.0"},{"key":"Implementation-Title","value":"kotlin-reflect"},{"key":"Kotlin-Runtime-Component","value":"Main"},{"key":"Kotlin-Version","value":"1.6"},{"key":"Implementation-Version","value":"1.6.0-release-798(1.6.0)"},{"key":"Multi-Release","value":"true"},{"key":"Implementation-Vendor","value":"JetBrains"}]},"digest":[{"algorithm":"sha1","value":"bbb6cd34e54f0905361a71b94f11bc6e5d53faeb"}]}},{"id":"68b3ba9ddd5ab654","name":"kotlin-stdlib","version":"1.6.0","type":"java-archive","foundBy":"java-archive-cataloger","locations":[{"path":"/test/data/RPMTW-Update-Mod-Fabric-1.18.1-1.3.1.jar","accessPath":"/test/data/RPMTW-Update-Mod-Fabric-1.18.1-1.3.1.jar:META-INF/jars/fabric-language-kotlin-1.7.0+kotlin.1.6.0.jar:META-INF/jars/kotlin-stdlib-1.6.0.jar","annotations":{"evidence":"primary"}}],"licenses":[],"language":"java","cpes":[{"cpe":"cpe:2.3:a:kotlin-stdlib:kotlin-stdlib:1.6.0:*:*:*:*:*:*:*","source":"syft-generated"},{"cpe":"cpe:2.3:a:kotlin-stdlib:kotlin_stdlib:1.6.0:*:*:*:*:*:*:*","source":"syft-generated"},{"cpe":"cpe:2.3:a:kotlin_stdlib:kotlin-stdlib:1.6.0:*:*:*:*:*:*:*","source":"syft-generated"},{"cpe":"cpe:2.3:a:kotlin_stdlib:kotlin_stdlib:1.6.0:*:*:*:*:*:*:*","source":"syft-generated"},{"cpe":"cpe:2.3:a:jetbrains:kotlin-stdlib:1.6.0:*:*:*:*:*:*:*","source":"syft-generated"},{"cpe":"cpe:2.3:a:jetbrains:kotlin_stdlib:1.6.0:*:*:*:*:*:*:*","source":"syft-generated"},{"cpe":"cpe:2.3:a:kotlin:kotlin-stdlib:1.6.0:*:*:*:*:*:*:*","source":"syft-generated"},{"cpe":"cpe:2.3:a:kotlin:kotlin_stdlib:1.6.0:*:*:*:*:*:*:*","source":"syft-generated"}],"purl":"pkg:maven/kotlin-stdlib/kotlin-stdlib@1.6.0","metadataType":"java-archive","metadata":{"virtualPath":"/test/data/RPMTW-Update-Mod-Fabric-1.18.1-1.3.1.jar:META-INF/jars/fabric-language-kotlin-1.7.0+kotlin.1.6.0.jar:META-INF/jars/kotlin-stdlib-1.6.0.jar","manifest":{"main":[{"key":"Manifest-Version","value":"1.0"},{"key":"Implementation-Title","value":"kotlin-stdlib"},{"key":"Kotlin-Runtime-Component","value":"Main"},{"key":"Kotlin-Version","value":"1.6"},{"key":"Implementation-Version","value":"1.6.0-release-798(1.6.0)"},{"key":"Multi-Release","value":"true"},{"key":"Implementation-Vendor","value":"JetBrains"}]},"digest":[{"algorithm":"sha1","value":"9104a4449d5650c45015c45aef7e159a65d7a27a"}]}},{"id":"b0e133ed3faac023","name":"kotlin-stdlib-jdk7","version":"1.6.0","type":"java-archive","foundBy":"java-archive-cataloger","locations":[{"path":"/test/data/RPMTW-Update-Mod-Fabric-1.18.1-1.3.1.jar","accessPath":"/test/data/RPMTW-Update-Mod-Fabric-1.18.1-1.3.1.jar:META-INF/jars/fabric-language-kotlin-1.7.0+kotlin.1.6.0.jar:META-INF/jars/kotlin-stdlib-jdk7-1.6.0.jar","annotations":{"evidence":"primary"}}],"licenses":[],"language":"java","cpes":[{"cpe":"cpe:2.3:a:kotlin-stdlib-jdk7:kotlin-stdlib-jdk7:1.6.0:*:*:*:*:*:*:*","source":"syft-generated"},{"cpe":"cpe:2.3:a:kotlin-stdlib-jdk7:kotlin_stdlib_jdk7:1.6.0:*:*:*:*:*:*:*","source":"syft-generated"},{"cpe":"cpe:2.3:a:kotlin_stdlib_jdk7:kotlin-stdlib-jdk7:1.6.0:*:*:*:*:*:*:*","source":"syft-generated"},{"cpe":"cpe:2.3:a:kotlin_stdlib_jdk7:kotlin_stdlib_jdk7:1.6.0:*:*:*:*:*:*:*","source":"syft-generated"},{"cpe":"cpe:2.3:a:kotlin-stdlib:kotlin-stdlib-jdk7:1.6.0:*:*:*:*:*:*:*","source":"syft-generated"},{"cpe":"cpe:2.3:a:kotlin-stdlib:kotlin_stdlib_jdk7:1.6.0:*:*:*:*:*:*:*","source":"syft-generated"},{"cpe":"cpe:2.3:a:kotlin_stdlib:kotlin-stdlib-jdk7:1.6.0:*:*:*:*:*:*:*","source":"syft-generated"},{"cpe":"cpe:2.3:a:kotlin_stdlib:kotlin_stdlib_jdk7:1.6.0:*:*:*:*:*:*:*","source":"syft-generated"},{"cpe":"cpe:2.3:a:jetbrains:kotlin-stdlib-jdk7:1.6.0:*:*:*:*:*:*:*","source":"syft-generated"},{"cpe":"cpe:2.3:a:jetbrains:kotlin_stdlib_jdk7:1.6.0:*:*:*:*:*:*:*","source":"syft-generated"},{"cpe":"cpe:2.3:a:kotlin:kotlin-stdlib-jdk7:1.6.0:*:*:*:*:*:*:*","source":"syft-generated"},{"cpe":"cpe:2.3:a:kotlin:kotlin_stdlib_jdk7:1.6.0:*:*:*:*:*:*:*","source":"syft-generated"}],"purl":"pkg:maven/kotlin-stdlib-jdk7/kotlin-stdlib-jdk7@1.6.0","metadataType":"java-archive","metadata":{"virtualPath":"/test/data/RPMTW-Update-Mod-Fabric-1.18.1-1.3.1.jar:META-INF/jars/fabric-language-kotlin-1.7.0+kotlin.1.6.0.jar:META-INF/jars/kotlin-stdlib-jdk7-1.6.0.jar","manifest":{"main":[{"key":"Manifest-Version","value":"1.0"},{"key":"Implementation-Title","value":"kotlin-stdlib-jdk7"},{"key":"Kotlin-Runtime-Component","value":"Main"},{"key":"Kotlin-Version","value":"1.6"},{"key":"Implementation-Version","value":"1.6.0-release-798(1.6.0)"},{"key":"Multi-Release","value":"true"},{"key":"Implementation-Vendor","value":"JetBrains"}]},"digest":[{"algorithm":"sha1","value":"f9f4836c9e4905fc1ce79a147dbd884b3d73381f"}]}},{"id":"cf4403db8f648135","name":"kotlin-stdlib-jdk8","version":"1.6.0","type":"java-archive","foundBy":"java-archive-cataloger","locations":[{"path":"/test/data/RPMTW-Update-Mod-Fabric-1.18.1-1.3.1.jar","accessPath":"/test/data/RPMTW-Update-Mod-Fabric-1.18.1-1.3.1.jar:META-INF/jars/fabric-language-kotlin-1.7.0+kotlin.1.6.0.jar:META-INF/jars/kotlin-stdlib-jdk8-1.6.0.jar","annotations":{"evidence":"primary"}}],"licenses":[],"language":"java","cpes":[{"cpe":"cpe:2.3:a:kotlin-stdlib-jdk8:kotlin-stdlib-jdk8:1.6.0:*:*:*:*:*:*:*","source":"syft-generated"},{"cpe":"cpe:2.3:a:kotlin-stdlib-jdk8:kotlin_stdlib_jdk8:1.6.0:*:*:*:*:*:*:*","source":"syft-generated"},{"cpe":"cpe:2.3:a:kotlin_stdlib_jdk8:kotlin-stdlib-jdk8:1.6.0:*:*:*:*:*:*:*","source":"syft-generated"},{"cpe":"cpe:2.3:a:kotlin_stdlib_jdk8:kotlin_stdlib_jdk8:1.6.0:*:*:*:*:*:*:*","source":"syft-generated"},{"cpe":"cpe:2.3:a:kotlin-stdlib:kotlin-stdlib-jdk8:1.6.0:*:*:*:*:*:*:*","source":"syft-generated"},{"cpe":"cpe:2.3:a:kotlin-stdlib:kotlin_stdlib_jdk8:1.6.0:*:*:*:*:*:*:*","source":"syft-generated"},{"cpe":"cpe:2.3:a:kotlin_stdlib:kotlin-stdlib-jdk8:1.6.0:*:*:*:*:*:*:*","source":"syft-generated"},{"cpe":"cpe:2.3:a:kotlin_stdlib:kotlin_stdlib_jdk8:1.6.0:*:*:*:*:*:*:*","source":"syft-generated"},{"cpe":"cpe:2.3:a:jetbrains:kotlin-stdlib-jdk8:1.6.0:*:*:*:*:*:*:*","source":"syft-generated"},{"cpe":"cpe:2.3:a:jetbrains:kotlin_stdlib_jdk8:1.6.0:*:*:*:*:*:*:*","source":"syft-generated"},{"cpe":"cpe:2.3:a:kotlin:kotlin-stdlib-jdk8:1.6.0:*:*:*:*:*:*:*","source":"syft-generated"},{"cpe":"cpe:2.3:a:kotlin:kotlin_stdlib_jdk8:1.6.0:*:*:*:*:*:*:*","source":"syft-generated"}],"purl":"pkg:maven/kotlin-stdlib-jdk8/kotlin-stdlib-jdk8@1.6.0","metadataType":"java-archive","metadata":{"virtualPath":"/test/data/RPMTW-Update-Mod-Fabric-1.18.1-1.3.1.jar:META-INF/jars/fabric-language-kotlin-1.7.0+kotlin.1.6.0.jar:META-INF/jars/kotlin-stdlib-jdk8-1.6.0.jar","manifest":{"main":[{"key":"Manifest-Version","value":"1.0"},{"key":"Implementation-Title","value":"kotlin-stdlib-jdk8"},{"key":"Kotlin-Runtime-Component","value":"Main"},{"key":"Kotlin-Version","value":"1.6"},{"key":"Implementation-Version","value":"1.6.0-release-798(1.6.0)"},{"key":"Multi-Release","value":"true"},{"key":"Implementation-Vendor","value":"JetBrains"}]},"digest":[{"algorithm":"sha1","value":"48ddd520ee1bb786151175a5ea55be797cb39aa0"}]}},{"id":"66baf2235cda475c","name":"kotlinx-coroutines-core-jvm","version":"1.5.2","type":"java-archive","foundBy":"java-archive-cataloger","locations":[{"path":"/test/data/RPMTW-Update-Mod-Fabric-1.18.1-1.3.1.jar","accessPath":"/test/data/RPMTW-Update-Mod-Fabric-1.18.1-1.3.1.jar:META-INF/jars/fabric-language-kotlin-1.7.0+kotlin.1.6.0.jar:META-INF/jars/kotlinx-coroutines-core-jvm-1.5.2.jar","annotations":{"evidence":"primary"}}],"licenses":[],"language":"java","cpes":[{"cpe":"cpe:2.3:a:kotlinx-coroutines-core-jvm:kotlinx-coroutines-core-jvm:1.5.2:*:*:*:*:*:*:*","source":"syft-generated"},{"cpe":"cpe:2.3:a:kotlinx-coroutines-core-jvm:kotlinx_coroutines_core_jvm:1.5.2:*:*:*:*:*:*:*","source":"syft-generated"},{"cpe":"cpe:2.3:a:kotlinx_coroutines_core_jvm:kotlinx-coroutines-core-jvm:1.5.2:*:*:*:*:*:*:*","source":"syft-generated"},{"cpe":"cpe:2.3:a:kotlinx_coroutines_core_jvm:kotlinx_coroutines_core_jvm:1.5.2:*:*:*:*:*:*:*","source":"syft-generated"},{"cpe":"cpe:2.3:a:kotlinx-coroutines-core:kotlinx-coroutines-core-jvm:1.5.2:*:*:*:*:*:*:*","source":"syft-generated"},{"cpe":"cpe:2.3:a:kotlinx-coroutines-core:kotlinx_coroutines_core_jvm:1.5.2:*:*:*:*:*:*:*","source":"syft-generated"},{"cpe":"cpe:2.3:a:kotlinx_coroutines_core:kotlinx-coroutines-core-jvm:1.5.2:*:*:*:*:*:*:*","source":"syft-generated"},{"cpe":"cpe:2.3:a:kotlinx_coroutines_core:kotlinx_coroutines_core_jvm:1.5.2:*:*:*:*:*:*:*","source":"syft-generated"},{"cpe":"cpe:2.3:a:kotlinx-coroutines:kotlinx-coroutines-core-jvm:1.5.2:*:*:*:*:*:*:*","source":"syft-generated"},{"cpe":"cpe:2.3:a:kotlinx-coroutines:kotlinx_coroutines_core_jvm:1.5.2:*:*:*:*:*:*:*","source":"syft-generated"},{"cpe":"cpe:2.3:a:kotlinx_coroutines:kotlinx-coroutines-core-jvm:1.5.2:*:*:*:*:*:*:*","source":"syft-generated"},{"cpe":"cpe:2.3:a:kotlinx_coroutines:kotlinx_coroutines_core_jvm:1.5.2:*:*:*:*:*:*:*","source":"syft-generated"},{"cpe":"cpe:2.3:a:kotlinx:kotlinx-coroutines-core-jvm:1.5.2:*:*:*:*:*:*:*","source":"syft-generated"},{"cpe":"cpe:2.3:a:kotlinx:kotlinx_coroutines_core_jvm:1.5.2:*:*:*:*:*:*:*","source":"syft-generated"}],"purl":"pkg:maven/kotlinx-coroutines-core-jvm/kotlinx-coroutines-core-jvm@1.5.2","metadataType":"java-archive","metadata":{"virtualPath":"/test/data/RPMTW-Update-Mod-Fabric-1.18.1-1.3.1.jar:META-INF/jars/fabric-language-kotlin-1.7.0+kotlin.1.6.0.jar:META-INF/jars/kotlinx-coroutines-core-jvm-1.5.2.jar","manifest":{"main":[{"key":"Manifest-Version","value":"1.0"},{"key":"Premain-Class","value":"kotlinx.coroutines.debug.AgentPremain"},{"key":"Can-Retransform-Classes","value":"true"}]},"digest":[{"algorithm":"sha1","value":"81f39f25f8dc8327a33c1724a4c9bb2a949bd27a"}]}},{"id":"65a81a7b1688b191","name":"kotlinx-coroutines-jdk8","version":"1.5.2","type":"java-archive","foundBy":"java-archive-cataloger","locations":[{"path":"/test/data/RPMTW-Update-Mod-Fabric-1.18.1-1.3.1.jar","accessPath":"/test/data/RPMTW-Update-Mod-Fabric-1.18.1-1.3.1.jar:META-INF/jars/fabric-language-kotlin-1.7.0+kotlin.1.6.0.jar:META-INF/jars/kotlinx-coroutines-jdk8-1.5.2.jar","annotations":{"evidence":"primary"}}],"licenses":[],"language":"java","cpes":[{"cpe":"cpe:2.3:a:kotlinx-coroutines-jdk8:kotlinx-coroutines-jdk8:1.5.2:*:*:*:*:*:*:*","source":"syft-generated"},{"cpe":"cpe:2.3:a:kotlinx-coroutines-jdk8:kotlinx_coroutines_jdk8:1.5.2:*:*:*:*:*:*:*","source":"syft-generated"},{"cpe":"cpe:2.3:a:kotlinx_coroutines_jdk8:kotlinx-coroutines-jdk8:1.5.2:*:*:*:*:*:*:*","source":"syft-generated"},{"cpe":"cpe:2.3:a:kotlinx_coroutines_jdk8:kotlinx_coroutines_jdk8:1.5.2:*:*:*:*:*:*:*","source":"syft-generated"},{"cpe":"cpe:2.3:a:kotlinx-coroutines:kotlinx-coroutines-jdk8:1.5.2:*:*:*:*:*:*:*","source":"syft-generated"},{"cpe":"cpe:2.3:a:kotlinx-coroutines:kotlinx_coroutines_jdk8:1.5.2:*:*:*:*:*:*:*","source":"syft-generated"},{"cpe":"cpe:2.3:a:kotlinx_coroutines:kotlinx-coroutines-jdk8:1.5.2:*:*:*:*:*:*:*","source":"syft-generated"},{"cpe":"cpe:2.3:a:kotlinx_coroutines:kotlinx_coroutines_jdk8:1.5.2:*:*:*:*:*:*:*","source":"syft-generated"},{"cpe":"cpe:2.3:a:kotlinx:kotlinx-coroutines-jdk8:1.5.2:*:*:*:*:*:*:*","source":"syft-generated"},{"cpe":"cpe:2.3:a:kotlinx:kotlinx_coroutines_jdk8:1.5.2:*:*:*:*:*:*:*","source":"syft-generated"}],"purl":"pkg:maven/kotlinx-coroutines-jdk8/kotlinx-coroutines-jdk8@1.5.2","metadataType":"java-archive","metadata":{"virtualPath":"/test/data/RPMTW-Update-Mod-Fabric-1.18.1-1.3.1.jar:META-INF/jars/fabric-language-kotlin-1.7.0+kotlin.1.6.0.jar:META-INF/jars/kotlinx-coroutines-jdk8-1.5.2.jar","manifest":{"main":[{"key":"Manifest-Version","value":"1.0"}]},"digest":[{"algorithm":"sha1","value":"d6cff8f5a0b4c9a29bbe233cd4769cb11d08085e"}]}},{"id":"99be8abfab734041","name":"kotlinx-serialization-cbor-jvm","version":"1.3.1","type":"java-archive","foundBy":"java-archive-cataloger","locations":[{"path":"/test/data/RPMTW-Update-Mod-Fabric-1.18.1-1.3.1.jar","accessPath":"/test/data/RPMTW-Update-Mod-Fabric-1.18.1-1.3.1.jar:META-INF/jars/fabric-language-kotlin-1.7.0+kotlin.1.6.0.jar:META-INF/jars/kotlinx-serialization-cbor-jvm-1.3.1.jar","annotations":{"evidence":"primary"}}],"licenses":[],"language":"java","cpes":[{"cpe":"cpe:2.3:a:kotlinx-serialization-cbor-jvm:kotlinx-serialization-cbor-jvm:1.3.1:*:*:*:*:*:*:*","source":"syft-generated"},{"cpe":"cpe:2.3:a:kotlinx-serialization-cbor-jvm:kotlinx_serialization_cbor_jvm:1.3.1:*:*:*:*:*:*:*","source":"syft-generated"},{"cpe":"cpe:2.3:a:kotlinx_serialization_cbor_jvm:kotlinx-serialization-cbor-jvm:1.3.1:*:*:*:*:*:*:*","source":"syft-generated"},{"cpe":"cpe:2.3:a:kotlinx_serialization_cbor_jvm:kotlinx_serialization_cbor_jvm:1.3.1:*:*:*:*:*:*:*","source":"syft-generated"},{"cpe":"cpe:2.3:a:kotlinx-serialization-cbor:kotlinx-serialization-cbor-jvm:1.3.1:*:*:*:*:*:*:*","source":"syft-generated"},{"cpe":"cpe:2.3:a:kotlinx-serialization-cbor:kotlinx_serialization_cbor_jvm:1.3.1:*:*:*:*:*:*:*","source":"syft-generated"},{"cpe":"cpe:2.3:a:kotlinx_serialization_cbor:kotlinx-serialization-cbor-jvm:1.3.1:*:*:*:*:*:*:*","source":"syft-generated"},{"cpe":"cpe:2.3:a:kotlinx_serialization_cbor:kotlinx_serialization_cbor_jvm:1.3.1:*:*:*:*:*:*:*","source":"syft-generated"},{"cpe":"cpe:2.3:a:kotlinx-serialization:kotlinx-serialization-cbor-jvm:1.3.1:*:*:*:*:*:*:*","source":"syft-generated"},{"cpe":"cpe:2.3:a:kotlinx-serialization:kotlinx_serialization_cbor_jvm:1.3.1:*:*:*:*:*:*:*","source":"syft-generated"},{"cpe":"cpe:2.3:a:kotlinx_serialization:kotlinx-serialization-cbor-jvm:1.3.1:*:*:*:*:*:*:*","source":"syft-generated"},{"cpe":"cpe:2.3:a:kotlinx_serialization:kotlinx_serialization_cbor_jvm:1.3.1:*:*:*:*:*:*:*","source":"syft-generated"},{"cpe":"cpe:2.3:a:kotlinx:kotlinx-serialization-cbor-jvm:1.3.1:*:*:*:*:*:*:*","source":"syft-generated"},{"cpe":"cpe:2.3:a:kotlinx:kotlinx_serialization_cbor_jvm:1.3.1:*:*:*:*:*:*:*","source":"syft-generated"}],"purl":"pkg:maven/kotlinx-serialization-cbor-jvm/kotlinx-serialization-cbor-jvm@1.3.1","metadataType":"java-archive","metadata":{"virtualPath":"/test/data/RPMTW-Update-Mod-Fabric-1.18.1-1.3.1.jar:META-INF/jars/fabric-language-kotlin-1.7.0+kotlin.1.6.0.jar:META-INF/jars/kotlinx-serialization-cbor-jvm-1.3.1.jar","manifest":{"main":[{"key":"Manifest-Version","value":"1.0"},{"key":"Multi-Release","value":"true"}]},"digest":[{"algorithm":"sha1","value":"be0070ba756e488c774d38f306f7bc143ec56f26"}]}},{"id":"956ba2c065a0c99d","name":"kotlinx-serialization-core-jvm","version":"1.3.1","type":"java-archive","foundBy":"java-archive-cataloger","locations":[{"path":"/test/data/RPMTW-Update-Mod-Fabric-1.18.1-1.3.1.jar","accessPath":"/test/data/RPMTW-Update-Mod-Fabric-1.18.1-1.3.1.jar:META-INF/jars/fabric-language-kotlin-1.7.0+kotlin.1.6.0.jar:META-INF/jars/kotlinx-serialization-core-jvm-1.3.1.jar","annotations":{"evidence":"primary"}}],"licenses":[],"language":"java","cpes":[{"cpe":"cpe:2.3:a:kotlinx-serialization-core-jvm:kotlinx-serialization-core-jvm:1.3.1:*:*:*:*:*:*:*","source":"syft-generated"},{"cpe":"cpe:2.3:a:kotlinx-serialization-core-jvm:kotlinx_serialization_core_jvm:1.3.1:*:*:*:*:*:*:*","source":"syft-generated"},{"cpe":"cpe:2.3:a:kotlinx_serialization_core_jvm:kotlinx-serialization-core-jvm:1.3.1:*:*:*:*:*:*:*","source":"syft-generated"},{"cpe":"cpe:2.3:a:kotlinx_serialization_core_jvm:kotlinx_serialization_core_jvm:1.3.1:*:*:*:*:*:*:*","source":"syft-generated"},{"cpe":"cpe:2.3:a:kotlinx-serialization-core:kotlinx-serialization-core-jvm:1.3.1:*:*:*:*:*:*:*","source":"syft-generated"},{"cpe":"cpe:2.3:a:kotlinx-serialization-core:kotlinx_serialization_core_jvm:1.3.1:*:*:*:*:*:*:*","source":"syft-generated"},{"cpe":"cpe:2.3:a:kotlinx_serialization_core:kotlinx-serialization-core-jvm:1.3.1:*:*:*:*:*:*:*","source":"syft-generated"},{"cpe":"cpe:2.3:a:kotlinx_serialization_core:kotlinx_serialization_core_jvm:1.3.1:*:*:*:*:*:*:*","source":"syft-generated"},{"cpe":"cpe:2.3:a:kotlinx-serialization:kotlinx-serialization-core-jvm:1.3.1:*:*:*:*:*:*:*","source":"syft-generated"},{"cpe":"cpe:2.3:a:kotlinx-serialization:kotlinx_serialization_core_jvm:1.3.1:*:*:*:*:*:*:*","source":"syft-generated"},{"cpe":"cpe:2.3:a:kotlinx_serialization:kotlinx-serialization-core-jvm:1.3.1:*:*:*:*:*:*:*","source":"syft-generated"},{"cpe":"cpe:2.3:a:kotlinx_serialization:kotlinx_serialization_core_jvm:1.3.1:*:*:*:*:*:*:*","source":"syft-generated"},{"cpe":"cpe:2.3:a:kotlinx:kotlinx-serialization-core-jvm:1.3.1:*:*:*:*:*:*:*","source":"syft-generated"},{"cpe":"cpe:2.3:a:kotlinx:kotlinx_serialization_core_jvm:1.3.1:*:*:*:*:*:*:*","source":"syft-generated"}],"purl":"pkg:maven/kotlinx-serialization-core-jvm/kotlinx-serialization-core-jvm@1.3.1","metadataType":"java-archive","metadata":{"virtualPath":"/test/data/RPMTW-Update-Mod-Fabric-1.18.1-1.3.1.jar:META-INF/jars/fabric-language-kotlin-1.7.0+kotlin.1.6.0.jar:META-INF/jars/kotlinx-serialization-core-jvm-1.3.1.jar","manifest":{"main":[{"key":"Manifest-Version","value":"1.0"},{"key":"Implementation-Version","value":"1.3.1"},{"key":"Require-Kotlin-Version","value":"1.4.30-M1"},{"key":"Multi-Release","value":"true"}]},"digest":[{"algorithm":"sha1","value":"1dff41a1d1b4c104b135b9a18fd82796c4124def"}]}},{"id":"654efdcd7ff571d3","name":"kotlinx-serialization-json-jvm","version":"1.3.1","type":"java-archive","foundBy":"java-archive-cataloger","locations":[{"path":"/test/data/RPMTW-Update-Mod-Fabric-1.18.1-1.3.1.jar","accessPath":"/test/data/RPMTW-Update-Mod-Fabric-1.18.1-1.3.1.jar:META-INF/jars/fabric-language-kotlin-1.7.0+kotlin.1.6.0.jar:META-INF/jars/kotlinx-serialization-json-jvm-1.3.1.jar","annotations":{"evidence":"primary"}}],"licenses":[],"language":"java","cpes":[{"cpe":"cpe:2.3:a:kotlinx-serialization-json-jvm:kotlinx-serialization-json-jvm:1.3.1:*:*:*:*:*:*:*","source":"syft-generated"},{"cpe":"cpe:2.3:a:kotlinx-serialization-json-jvm:kotlinx_serialization_json_jvm:1.3.1:*:*:*:*:*:*:*","source":"syft-generated"},{"cpe":"cpe:2.3:a:kotlinx_serialization_json_jvm:kotlinx-serialization-json-jvm:1.3.1:*:*:*:*:*:*:*","source":"syft-generated"},{"cpe":"cpe:2.3:a:kotlinx_serialization_json_jvm:kotlinx_serialization_json_jvm:1.3.1:*:*:*:*:*:*:*","source":"syft-generated"},{"cpe":"cpe:2.3:a:kotlinx-serialization-json:kotlinx-serialization-json-jvm:1.3.1:*:*:*:*:*:*:*","source":"syft-generated"},{"cpe":"cpe:2.3:a:kotlinx-serialization-json:kotlinx_serialization_json_jvm:1.3.1:*:*:*:*:*:*:*","source":"syft-generated"},{"cpe":"cpe:2.3:a:kotlinx_serialization_json:kotlinx-serialization-json-jvm:1.3.1:*:*:*:*:*:*:*","source":"syft-generated"},{"cpe":"cpe:2.3:a:kotlinx_serialization_json:kotlinx_serialization_json_jvm:1.3.1:*:*:*:*:*:*:*","source":"syft-generated"},{"cpe":"cpe:2.3:a:kotlinx-serialization:kotlinx-serialization-json-jvm:1.3.1:*:*:*:*:*:*:*","source":"syft-generated"},{"cpe":"cpe:2.3:a:kotlinx-serialization:kotlinx_serialization_json_jvm:1.3.1:*:*:*:*:*:*:*","source":"syft-generated"},{"cpe":"cpe:2.3:a:kotlinx_serialization:kotlinx-serialization-json-jvm:1.3.1:*:*:*:*:*:*:*","source":"syft-generated"},{"cpe":"cpe:2.3:a:kotlinx_serialization:kotlinx_serialization_json_jvm:1.3.1:*:*:*:*:*:*:*","source":"syft-generated"},{"cpe":"cpe:2.3:a:kotlinx:kotlinx-serialization-json-jvm:1.3.1:*:*:*:*:*:*:*","source":"syft-generated"},{"cpe":"cpe:2.3:a:kotlinx:kotlinx_serialization_json_jvm:1.3.1:*:*:*:*:*:*:*","source":"syft-generated"}],"purl":"pkg:maven/kotlinx-serialization-json-jvm/kotlinx-serialization-json-jvm@1.3.1","metadataType":"java-archive","metadata":{"virtualPath":"/test/data/RPMTW-Update-Mod-Fabric-1.18.1-1.3.1.jar:META-INF/jars/fabric-language-kotlin-1.7.0+kotlin.1.6.0.jar:META-INF/jars/kotlinx-serialization-json-jvm-1.3.1.jar","manifest":{"main":[{"key":"Manifest-Version","value":"1.0"},{"key":"Multi-Release","value":"true"}]},"digest":[{"algorithm":"sha1","value":"e1257b417c7a61ad58f52ce27e7ca0df03fd11a1"}]}},{"id":"05789099fb338fbb","name":"libninepatch","version":"1.1.0","type":"java-archive","foundBy":"java-archive-cataloger","locations":[{"path":"/test/data/RPMTW-Update-Mod-Fabric-1.18.1-1.3.1.jar","accessPath":"/test/data/RPMTW-Update-Mod-Fabric-1.18.1-1.3.1.jar:META-INF/jars/LibGui-5.3.1+1.18.jar:META-INF/jars/libninepatch-1.1.0.jar","annotations":{"evidence":"primary"}}],"licenses":[{"value":"MPL-2.0","spdxExpression":"MPL-2.0","type":"concluded","urls":[],"locations":[{"path":"/test/data/RPMTW-Update-Mod-Fabric-1.18.1-1.3.1.jar","accessPath":"/test/data/RPMTW-Update-Mod-Fabric-1.18.1-1.3.1.jar:META-INF/jars/LibGui-5.3.1+1.18.jar:META-INF/jars/libninepatch-1.1.0.jar","annotations":{"evidence":"primary"}}]}],"language":"java","cpes":[{"cpe":"cpe:2.3:a:libninepatch:libninepatch:1.1.0:*:*:*:*:*:*:*","source":"syft-generated"}],"purl":"pkg:maven/libninepatch/libninepatch@1.1.0","metadataType":"java-archive","metadata":{"virtualPath":"/test/data/RPMTW-Update-Mod-Fabric-1.18.1-1.3.1.jar:META-INF/jars/LibGui-5.3.1+1.18.jar:META-INF/jars/libninepatch-1.1.0.jar","manifest":{"main":[{"key":"Manifest-Version","value":"1.0"}]},"digest":[{"algorithm":"sha1","value":"15290044f9097b4a828638c24cba3dfa5f28fab5"}]}},{"id":"461cd66b2aa69acd","name":"libninepatch","version":"1.1.0","type":"java-archive","foundBy":"java-archive-cataloger","locations":[{"path":"/test/data/RPMTW-Update-Mod-Fabric-1.18.1-1.3.1.jar","accessPath":"/test/data/RPMTW-Update-Mod-Fabric-1.18.1-1.3.1.jar:META-INF/jars/libninepatch-1.1.0.jar","annotations":{"evidence":"primary"}}],"licenses":[{"value":"MPL-2.0","spdxExpression":"MPL-2.0","type":"concluded","urls":[],"locations":[{"path":"/test/data/RPMTW-Update-Mod-Fabric-1.18.1-1.3.1.jar","accessPath":"/test/data/RPMTW-Update-Mod-Fabric-1.18.1-1.3.1.jar:META-INF/jars/libninepatch-1.1.0.jar","annotations":{"evidence":"primary"}}]}],"language":"java","cpes":[{"cpe":"cpe:2.3:a:libninepatch:libninepatch:1.1.0:*:*:*:*:*:*:*","source":"syft-generated"}],"purl":"pkg:maven/libninepatch/libninepatch@1.1.0","metadataType":"java-archive","metadata":{"virtualPath":"/test/data/RPMTW-Update-Mod-Fabric-1.18.1-1.3.1.jar:META-INF/jars/libninepatch-1.1.0.jar","manifest":{"main":[{"key":"Manifest-Version","value":"1.0"}]},"digest":[{"algorithm":"sha1","value":"15290044f9097b4a828638c24cba3dfa5f28fab5"}]}},{"id":"c8a5569efd83caa5","name":"okhttp","version":"4.9.3","type":"java-archive","foundBy":"java-archive-cataloger","locations":[{"path":"/test/data/RPMTW-Update-Mod-Fabric-1.18.1-1.3.1.jar","accessPath":"/test/data/RPMTW-Update-Mod-Fabric-1.18.1-1.3.1.jar:META-INF/jars/okhttp-4.9.3.jar","annotations":{"evidence":"primary"}}],"licenses":[],"language":"java","cpes":[{"cpe":"cpe:2.3:a:com.squareup.okhttp3:okhttp3:4.9.3:*:*:*:*:*:*:*","source":"syft-generated"},{"cpe":"cpe:2.3:a:com.squareup.okhttp3:okhttp:4.9.3:*:*:*:*:*:*:*","source":"syft-generated"},{"cpe":"cpe:2.3:a:squareup:okhttp3:4.9.3:*:*:*:*:*:*:*","source":"syft-generated"},{"cpe":"cpe:2.3:a:okhttp3:okhttp3:4.9.3:*:*:*:*:*:*:*","source":"syft-generated"},{"cpe":"cpe:2.3:a:squareup:okhttp:4.9.3:*:*:*:*:*:*:*","source":"syft-generated"},{"cpe":"cpe:2.3:a:okhttp3:okhttp:4.9.3:*:*:*:*:*:*:*","source":"syft-generated"},{"cpe":"cpe:2.3:a:okhttp:okhttp3:4.9.3:*:*:*:*:*:*:*","source":"syft-generated"},{"cpe":"cpe:2.3:a:okhttp:okhttp:4.9.3:*:*:*:*:*:*:*","source":"syft-generated"}],"purl":"pkg:maven/com.squareup.okhttp3/okhttp@4.9.3","metadataType":"java-archive","metadata":{"virtualPath":"/test/data/RPMTW-Update-Mod-Fabric-1.18.1-1.3.1.jar:META-INF/jars/okhttp-4.9.3.jar","manifest":{"main":[{"key":"Manifest-Version","value":"1.0"},{"key":"Automatic-Module-Name","value":"okhttp3"}]},"digest":[{"algorithm":"sha1","value":"36100c72a5cf74af0b95365d77583cf76b97cb5a"}]}},{"id":"001f7e2e821249e6","name":"okio-jvm","version":"2.10.0","type":"java-archive","foundBy":"java-archive-cataloger","locations":[{"path":"/test/data/RPMTW-Update-Mod-Fabric-1.18.1-1.3.1.jar","accessPath":"/test/data/RPMTW-Update-Mod-Fabric-1.18.1-1.3.1.jar:META-INF/jars/okio-jvm-2.10.0.jar","annotations":{"evidence":"primary"}}],"licenses":[],"language":"java","cpes":[{"cpe":"cpe:2.3:a:com.squareup.okio:okio-jvm:2.10.0:*:*:*:*:*:*:*","source":"syft-generated"},{"cpe":"cpe:2.3:a:com.squareup.okio:okio_jvm:2.10.0:*:*:*:*:*:*:*","source":"syft-generated"},{"cpe":"cpe:2.3:a:com.squareup.okio:okio:2.10.0:*:*:*:*:*:*:*","source":"syft-generated"},{"cpe":"cpe:2.3:a:okio-jvm:okio-jvm:2.10.0:*:*:*:*:*:*:*","source":"syft-generated"},{"cpe":"cpe:2.3:a:okio-jvm:okio_jvm:2.10.0:*:*:*:*:*:*:*","source":"syft-generated"},{"cpe":"cpe:2.3:a:okio_jvm:okio-jvm:2.10.0:*:*:*:*:*:*:*","source":"syft-generated"},{"cpe":"cpe:2.3:a:okio_jvm:okio_jvm:2.10.0:*:*:*:*:*:*:*","source":"syft-generated"},{"cpe":"cpe:2.3:a:squareup:okio-jvm:2.10.0:*:*:*:*:*:*:*","source":"syft-generated"},{"cpe":"cpe:2.3:a:squareup:okio_jvm:2.10.0:*:*:*:*:*:*:*","source":"syft-generated"},{"cpe":"cpe:2.3:a:okio-jvm:okio:2.10.0:*:*:*:*:*:*:*","source":"syft-generated"},{"cpe":"cpe:2.3:a:okio:okio-jvm:2.10.0:*:*:*:*:*:*:*","source":"syft-generated"},{"cpe":"cpe:2.3:a:okio:okio_jvm:2.10.0:*:*:*:*:*:*:*","source":"syft-generated"},{"cpe":"cpe:2.3:a:okio_jvm:okio:2.10.0:*:*:*:*:*:*:*","source":"syft-generated"},{"cpe":"cpe:2.3:a:squareup:okio:2.10.0:*:*:*:*:*:*:*","source":"syft-generated"},{"cpe":"cpe:2.3:a:okio:okio:2.10.0:*:*:*:*:*:*:*","source":"syft-generated"}],"purl":"pkg:maven/com.squareup.okio/okio-jvm@2.10.0","metadataType":"java-archive","metadata":{"virtualPath":"/test/data/RPMTW-Update-Mod-Fabric-1.18.1-1.3.1.jar:META-INF/jars/okio-jvm-2.10.0.jar","manifest":{"main":[{"key":"Manifest-Version","value":"1.0"},{"key":"Automatic-Module-Name","value":"okio"},{"key":"Bnd-LastModified","value":"1610057700769"},{"key":"Bundle-ManifestVersion","value":"2"},{"key":"Bundle-Name","value":"com.squareup.okio"},{"key":"Bundle-SymbolicName","value":"com.squareup.okio"},{"key":"Bundle-Version","value":"2.10.0"},{"key":"Created-By","value":"15-loom (Oracle Corporation)"},{"key":"Export-Package","value":"okio;uses:=\"javax.crypto,kotlin,kotlin.annotation,kotlin.collections,kotlin.jvm,kotlin.jvm.functions,kotlin.jvm.internal\";version=\"2.10.0\""},{"key":"Import-Package","value":"javax.crypto,javax.crypto.spec,kotlin,kotlin.annotation,kotlin.collections,kotlin.jvm,kotlin.jvm.functions,kotlin.jvm.internal,kotlin.text"},{"key":"Private-Package","value":"okio.internal"},{"key":"Require-Capability","value":"osgi.ee;filter:=\"(&(osgi.ee=JavaSE)(version=1.6))\""},{"key":"Tool","value":"Bnd-5.1.2.202007211702"}]},"digest":[{"algorithm":"sha1","value":"84c518dfcf8905801ee3e8431a941c6df299f957"}]}},{"id":"61792a3d9f409395","name":"snakeyaml","version":"1.27","type":"java-archive","foundBy":"java-archive-cataloger","locations":[{"path":"/test/data/RPMTW-Update-Mod-Fabric-1.18.1-1.3.1.jar","accessPath":"/test/data/RPMTW-Update-Mod-Fabric-1.18.1-1.3.1.jar:META-INF/jars/cloth-config-fabric-6.1.48.jar","annotations":{"evidence":"primary"}}],"licenses":[{"value":"Apache License, Version 2.0","spdxExpression":"","type":"declared","urls":["http://www.apache.org/licenses/LICENSE-2.0.txt"],"locations":[{"path":"/test/data/RPMTW-Update-Mod-Fabric-1.18.1-1.3.1.jar","accessPath":"/test/data/RPMTW-Update-Mod-Fabric-1.18.1-1.3.1.jar:META-INF/jars/cloth-config-fabric-6.1.48.jar","annotations":{"evidence":"primary"}}]}],"language":"java","cpes":[{"cpe":"cpe:2.3:a:snakeyaml:snakeyaml:1.27:*:*:*:*:*:*:*","source":"syft-generated"},{"cpe":"cpe:2.3:a:org.yaml:snakeyaml:1.27:*:*:*:*:*:*:*","source":"syft-generated"},{"cpe":"cpe:2.3:a:yaml:snakeyaml:1.27:*:*:*:*:*:*:*","source":"syft-generated"}],"purl":"pkg:maven/org.yaml/snakeyaml@1.27","metadataType":"java-archive","metadata":{"virtualPath":"/test/data/RPMTW-Update-Mod-Fabric-1.18.1-1.3.1.jar:META-INF/jars/cloth-config-fabric-6.1.48.jar:org.yaml:snakeyaml","pomProperties":{"path":"META-INF/maven/org.yaml/snakeyaml/pom.properties","name":"","groupId":"org.yaml","artifactId":"snakeyaml","version":"1.27"},"pomProject":{"path":"META-INF/maven/org.yaml/snakeyaml/pom.xml","groupId":"org.yaml","artifactId":"snakeyaml","version":"1.27","name":"SnakeYAML","description":"YAML 1.1 parser and emitter for Java","url":"http://www.snakeyaml.org"}}},{"id":"3328d45378335e9d","name":"socket.io-client","version":"2.0.1","type":"java-archive","foundBy":"java-archive-cataloger","locations":[{"path":"/test/data/RPMTW-Update-Mod-Fabric-1.18.1-1.3.1.jar","accessPath":"/test/data/RPMTW-Update-Mod-Fabric-1.18.1-1.3.1.jar:META-INF/jars/socket.io-client-2.0.1.jar","annotations":{"evidence":"primary"}}],"licenses":[{"value":"The MIT License (MIT)","spdxExpression":"","type":"declared","urls":["http://opensource.org/licenses/mit-license"],"locations":[{"path":"/test/data/RPMTW-Update-Mod-Fabric-1.18.1-1.3.1.jar","accessPath":"/test/data/RPMTW-Update-Mod-Fabric-1.18.1-1.3.1.jar:META-INF/jars/socket.io-client-2.0.1.jar","annotations":{"evidence":"primary"}}]}],"language":"java","cpes":[{"cpe":"cpe:2.3:a:socket.io-client:socket.io-client:2.0.1:*:*:*:*:*:*:*","source":"syft-generated"},{"cpe":"cpe:2.3:a:socket.io-client:socket.io_client:2.0.1:*:*:*:*:*:*:*","source":"syft-generated"},{"cpe":"cpe:2.3:a:socket.io_client:socket.io-client:2.0.1:*:*:*:*:*:*:*","source":"syft-generated"},{"cpe":"cpe:2.3:a:socket.io_client:socket.io_client:2.0.1:*:*:*:*:*:*:*","source":"syft-generated"},{"cpe":"cpe:2.3:a:io.socket:socket.io-client:2.0.1:*:*:*:*:*:*:*","source":"syft-generated"},{"cpe":"cpe:2.3:a:io.socket:socket.io_client:2.0.1:*:*:*:*:*:*:*","source":"syft-generated"},{"cpe":"cpe:2.3:a:socket.io:socket.io-client:2.0.1:*:*:*:*:*:*:*","source":"syft-generated"},{"cpe":"cpe:2.3:a:socket.io:socket.io_client:2.0.1:*:*:*:*:*:*:*","source":"syft-generated"},{"cpe":"cpe:2.3:a:socket:socket.io-client:2.0.1:*:*:*:*:*:*:*","source":"syft-generated"},{"cpe":"cpe:2.3:a:socket:socket.io_client:2.0.1:*:*:*:*:*:*:*","source":"syft-generated"}],"purl":"pkg:maven/io.socket/socket.io-client@2.0.1","metadataType":"java-archive","metadata":{"virtualPath":"/test/data/RPMTW-Update-Mod-Fabric-1.18.1-1.3.1.jar:META-INF/jars/socket.io-client-2.0.1.jar","manifest":{"main":[{"key":"Manifest-Version","value":"1.0"},{"key":"Archiver-Version","value":"Plexus Archiver"},{"key":"Built-By","value":"damien"},{"key":"Created-By","value":"Apache Maven 3.6.0"},{"key":"Build-Jdk","value":"1.8.0_282"}]},"pomProperties":{"path":"META-INF/maven/io.socket/socket.io-client/pom.properties","name":"","groupId":"io.socket","artifactId":"socket.io-client","version":"2.0.1"},"digest":[{"algorithm":"sha1","value":"4e4ee2bc49d5add45cec70ad48ccee06f4bb10a2"}]}},{"id":"2cf632ac0efee093","name":"toml4j","version":"0.7.2","type":"java-archive","foundBy":"java-archive-cataloger","locations":[{"path":"/test/data/RPMTW-Update-Mod-Fabric-1.18.1-1.3.1.jar","accessPath":"/test/data/RPMTW-Update-Mod-Fabric-1.18.1-1.3.1.jar:META-INF/jars/cloth-config-fabric-6.1.48.jar","annotations":{"evidence":"primary"}}],"licenses":[{"value":"The MIT License","spdxExpression":"","type":"declared","urls":["http://www.opensource.org/licenses/mit-license.php"],"locations":[{"path":"/test/data/RPMTW-Update-Mod-Fabric-1.18.1-1.3.1.jar","accessPath":"/test/data/RPMTW-Update-Mod-Fabric-1.18.1-1.3.1.jar:META-INF/jars/cloth-config-fabric-6.1.48.jar","annotations":{"evidence":"primary"}}]}],"language":"java","cpes":[{"cpe":"cpe:2.3:a:com.moandjiezana.toml:toml4j:0.7.2:*:*:*:*:*:*:*","source":"syft-generated"},{"cpe":"cpe:2.3:a:com.moandjiezana.toml:toml:0.7.2:*:*:*:*:*:*:*","source":"syft-generated"},{"cpe":"cpe:2.3:a:moandjiezana:toml4j:0.7.2:*:*:*:*:*:*:*","source":"syft-generated"},{"cpe":"cpe:2.3:a:moandjiezana:toml:0.7.2:*:*:*:*:*:*:*","source":"syft-generated"},{"cpe":"cpe:2.3:a:toml4j:toml4j:0.7.2:*:*:*:*:*:*:*","source":"syft-generated"},{"cpe":"cpe:2.3:a:toml4j:toml:0.7.2:*:*:*:*:*:*:*","source":"syft-generated"},{"cpe":"cpe:2.3:a:toml:toml4j:0.7.2:*:*:*:*:*:*:*","source":"syft-generated"},{"cpe":"cpe:2.3:a:toml:toml:0.7.2:*:*:*:*:*:*:*","source":"syft-generated"}],"purl":"pkg:maven/com.moandjiezana.toml/toml4j@0.7.2","metadataType":"java-archive","metadata":{"virtualPath":"/test/data/RPMTW-Update-Mod-Fabric-1.18.1-1.3.1.jar:META-INF/jars/cloth-config-fabric-6.1.48.jar:com.moandjiezana.toml:toml4j","pomProperties":{"path":"META-INF/maven/com.moandjiezana.toml/toml4j/pom.properties","name":"","groupId":"com.moandjiezana.toml","artifactId":"toml4j","version":"0.7.2"},"pomProject":{"path":"META-INF/maven/com.moandjiezana.toml/toml4j/pom.xml","groupId":"com.moandjiezana.toml","artifactId":"toml4j","version":"0.7.2","name":"toml4j","description":"A parser for TOML","url":"http://moandjiezana.com/toml/toml4j"}}},{"id":"a5c62215245023bf","name":"zip4j","version":"2.9.1","type":"java-archive","foundBy":"java-archive-cataloger","locations":[{"path":"/test/data/RPMTW-Update-Mod-Fabric-1.18.1-1.3.1.jar","accessPath":"/test/data/RPMTW-Update-Mod-Fabric-1.18.1-1.3.1.jar:META-INF/jars/zip4j-2.9.1.jar","annotations":{"evidence":"primary"}}],"licenses":[{"value":"https://www.apache.org/licenses/LICENSE-2.0.txt","spdxExpression":"","type":"declared","urls":[],"locations":[{"path":"/test/data/RPMTW-Update-Mod-Fabric-1.18.1-1.3.1.jar","accessPath":"/test/data/RPMTW-Update-Mod-Fabric-1.18.1-1.3.1.jar:META-INF/jars/zip4j-2.9.1.jar","annotations":{"evidence":"primary"}}]}],"language":"java","cpes":[{"cpe":"cpe:2.3:a:net.lingala.zip4j:zip4j:2.9.1:*:*:*:*:*:*:*","source":"syft-generated"},{"cpe":"cpe:2.3:a:lingala:zip4j:2.9.1:*:*:*:*:*:*:*","source":"syft-generated"},{"cpe":"cpe:2.3:a:zip4j:zip4j:2.9.1:*:*:*:*:*:*:*","source":"syft-generated"}],"purl":"pkg:maven/net.lingala.zip4j/zip4j@2.9.1","metadataType":"java-archive","metadata":{"virtualPath":"/test/data/RPMTW-Update-Mod-Fabric-1.18.1-1.3.1.jar:META-INF/jars/zip4j-2.9.1.jar","manifest":{"main":[{"key":"Manifest-Version","value":"1.0"},{"key":"Bnd-LastModified","value":"1637205523219"},{"key":"Build-Jdk","value":"1.8.0_192"},{"key":"Built-By","value":"slingala"},{"key":"Bundle-Description","value":"Zip4j - A Java library for zip files and streams"},{"key":"Bundle-License","value":"https://www.apache.org/licenses/LICENSE-2.0.txt"},{"key":"Bundle-ManifestVersion","value":"2"},{"key":"Bundle-Name","value":"Zip4j"},{"key":"Bundle-SymbolicName","value":"net.lingala.zip4j"},{"key":"Bundle-Version","value":"2.9.1"},{"key":"Created-By","value":"Apache Maven Bundle Plugin"},{"key":"Export-Package","value":"net.lingala.zip4j;uses:=\"net.lingala.zip4j.exception,net.lingala.zip4j.io.inputstream,net.lingala.zip4j.model,net.lingala.zip4j.progress\";version=\"2.9.1\",net.lingala.zip4j.crypto;uses:=\"net.lingala.zip4j.crypto.PBKDF2,net.lingala.zip4j.crypto.engine,net.lingala.zip4j.exception,net.lingala.zip4j.model,net.lingala.zip4j.model.enums\";version=\"2.9.1\",net.lingala.zip4j.crypto.PBKDF2;version=\"2.9.1\",net.lingala.zip4j.crypto.engine;uses:=\"net.lingala.zip4j.exception\";version=\"2.9.1\",net.lingala.zip4j.exception;version=\"2.9.1\",net.lingala.zip4j.headers;uses:=\"net.lingala.zip4j.exception,net.lingala.zip4j.io.outputstream,net.lingala.zip4j.model,net.lingala.zip4j.util\";version=\"2.9.1\",net.lingala.zip4j.io.inputstream;uses:=\"net.lingala.zip4j.model,net.lingala.zip4j.util\";version=\"2.9.1\",net.lingala.zip4j.io.outputstream;uses:=\"net.lingala.zip4j.exception,net.lingala.zip4j.model\";version=\"2.9.1\",net.lingala.zip4j.model;uses:=\"net.lingala.zip4j.headers,net.lingala.zip4j.model.enums\";version=\"2.9.1\",net.lingala.zip4j.model.enums;uses:=\"net.lingala.zip4j.exception\";version=\"2.9.1\",net.lingala.zip4j.progress;version=\"2.9.1\",net.lingala.zip4j.tasks;uses:=\"net.lingala.zip4j.exception,net.lingala.zip4j.headers,net.lingala.zip4j.io.inputstream,net.lingala.zip4j.model,net.lingala.zip4j.progress,net.lingala.zip4j.util\";version=\"2.9.1\",net.lingala.zip4j.util;uses:=\"net.lingala.zip4j.exception,net.lingala.zip4j.headers,net.lingala.zip4j.io.inputstream,net.lingala.zip4j.model,net.lingala.zip4j.model.enums,net.lingala.zip4j.progress\";version=\"2.9.1\""},{"key":"Import-Package","value":"javax.crypto,javax.crypto.spec,net.lingala.zip4j.crypto,net.lingala.zip4j.crypto.PBKDF2,net.lingala.zip4j.crypto.engine,net.lingala.zip4j.exception,net.lingala.zip4j.headers,net.lingala.zip4j.io.inputstream,net.lingala.zip4j.io.outputstream,net.lingala.zip4j.model,net.lingala.zip4j.model.enums,net.lingala.zip4j.progress,net.lingala.zip4j.tasks,net.lingala.zip4j.util"},{"key":"Require-Capability","value":"osgi.ee;filter:=\"(&(osgi.ee=JavaSE)(version=1.7))\""},{"key":"Tool","value":"Bnd-5.1.1.202006162103"}]},"pomProperties":{"path":"META-INF/maven/net.lingala.zip4j/zip4j/pom.properties","name":"","groupId":"net.lingala.zip4j","artifactId":"zip4j","version":"2.9.1"},"digest":[{"algorithm":"sha1","value":"be2975032cc589de5a41d72f3bd4cdd4ff71eec5"}]}}],"artifactRelationships":[{"parent":"001f7e2e821249e6","child":"76ddf373afcb14e6","type":"dependency-of"},{"parent":"001f7e2e821249e6","child":"e2e1da9ad39af790","type":"evident-by","metadata":{"kind":"primary"}},{"parent":"05789099fb338fbb","child":"e2e1da9ad39af790","type":"evident-by","metadata":{"kind":"primary"}},{"parent":"05789099fb338fbb","child":"f2a933110e480460","type":"dependency-of"},{"parent":"16babd937b1b697d7ec4fecad88e2922094191f04b56cf8320398ca893b7263f","child":"001f7e2e821249e6","type":"contains"},{"parent":"16babd937b1b697d7ec4fecad88e2922094191f04b56cf8320398ca893b7263f","child":"05789099fb338fbb","type":"contains"},{"parent":"16babd937b1b697d7ec4fecad88e2922094191f04b56cf8320398ca893b7263f","child":"2cf632ac0efee093","type":"contains"},{"parent":"16babd937b1b697d7ec4fecad88e2922094191f04b56cf8320398ca893b7263f","child":"3328d45378335e9d","type":"contains"},{"parent":"16babd937b1b697d7ec4fecad88e2922094191f04b56cf8320398ca893b7263f","child":"461cd66b2aa69acd","type":"contains"},{"parent":"16babd937b1b697d7ec4fecad88e2922094191f04b56cf8320398ca893b7263f","child":"5b9df2c05182116f","type":"contains"},{"parent":"16babd937b1b697d7ec4fecad88e2922094191f04b56cf8320398ca893b7263f","child":"5e557fbe1fd5aa47","type":"contains"},{"parent":"16babd937b1b697d7ec4fecad88e2922094191f04b56cf8320398ca893b7263f","child":"61792a3d9f409395","type":"contains"},{"parent":"16babd937b1b697d7ec4fecad88e2922094191f04b56cf8320398ca893b7263f","child":"654efdcd7ff571d3","type":"contains"},{"parent":"16babd937b1b697d7ec4fecad88e2922094191f04b56cf8320398ca893b7263f","child":"6592f001d39c2e5f","type":"contains"},{"parent":"16babd937b1b697d7ec4fecad88e2922094191f04b56cf8320398ca893b7263f","child":"65a81a7b1688b191","type":"contains"},{"parent":"16babd937b1b697d7ec4fecad88e2922094191f04b56cf8320398ca893b7263f","child":"66baf2235cda475c","type":"contains"},{"parent":"16babd937b1b697d7ec4fecad88e2922094191f04b56cf8320398ca893b7263f","child":"67b8e39e8d72c83b","type":"contains"},{"parent":"16babd937b1b697d7ec4fecad88e2922094191f04b56cf8320398ca893b7263f","child":"68b3ba9ddd5ab654","type":"contains"},{"parent":"16babd937b1b697d7ec4fecad88e2922094191f04b56cf8320398ca893b7263f","child":"76ddf373afcb14e6","type":"contains"},{"parent":"16babd937b1b697d7ec4fecad88e2922094191f04b56cf8320398ca893b7263f","child":"7fc119acc1ec15a7","type":"contains"},{"parent":"16babd937b1b697d7ec4fecad88e2922094191f04b56cf8320398ca893b7263f","child":"8b055904f3477773","type":"contains"},{"parent":"16babd937b1b697d7ec4fecad88e2922094191f04b56cf8320398ca893b7263f","child":"956ba2c065a0c99d","type":"contains"},{"parent":"16babd937b1b697d7ec4fecad88e2922094191f04b56cf8320398ca893b7263f","child":"99be8abfab734041","type":"contains"},{"parent":"16babd937b1b697d7ec4fecad88e2922094191f04b56cf8320398ca893b7263f","child":"a5c62215245023bf","type":"contains"},{"parent":"16babd937b1b697d7ec4fecad88e2922094191f04b56cf8320398ca893b7263f","child":"a8c63bf4c2aa6af6","type":"contains"},{"parent":"16babd937b1b697d7ec4fecad88e2922094191f04b56cf8320398ca893b7263f","child":"b0e133ed3faac023","type":"contains"},{"parent":"16babd937b1b697d7ec4fecad88e2922094191f04b56cf8320398ca893b7263f","child":"c8a5569efd83caa5","type":"contains"},{"parent":"16babd937b1b697d7ec4fecad88e2922094191f04b56cf8320398ca893b7263f","child":"cf4403db8f648135","type":"contains"},{"parent":"16babd937b1b697d7ec4fecad88e2922094191f04b56cf8320398ca893b7263f","child":"db3c1e8e251c4c2c","type":"contains"},{"parent":"16babd937b1b697d7ec4fecad88e2922094191f04b56cf8320398ca893b7263f","child":"f2a933110e480460","type":"contains"},{"parent":"16babd937b1b697d7ec4fecad88e2922094191f04b56cf8320398ca893b7263f","child":"f4d28eaf236a9002","type":"contains"},{"parent":"2cf632ac0efee093","child":"67b8e39e8d72c83b","type":"dependency-of"},{"parent":"2cf632ac0efee093","child":"e2e1da9ad39af790","type":"evident-by","metadata":{"kind":"primary"}},{"parent":"3328d45378335e9d","child":"76ddf373afcb14e6","type":"dependency-of"},{"parent":"3328d45378335e9d","child":"e2e1da9ad39af790","type":"evident-by","metadata":{"kind":"primary"}},{"parent":"461cd66b2aa69acd","child":"76ddf373afcb14e6","type":"dependency-of"},{"parent":"461cd66b2aa69acd","child":"e2e1da9ad39af790","type":"evident-by","metadata":{"kind":"primary"}},{"parent":"5b9df2c05182116f","child":"a8c63bf4c2aa6af6","type":"dependency-of"},{"parent":"5b9df2c05182116f","child":"e2e1da9ad39af790","type":"evident-by","metadata":{"kind":"primary"}},{"parent":"5e557fbe1fd5aa47","child":"e2e1da9ad39af790","type":"evident-by","metadata":{"kind":"primary"}},{"parent":"5e557fbe1fd5aa47","child":"f2a933110e480460","type":"dependency-of"},{"parent":"61792a3d9f409395","child":"67b8e39e8d72c83b","type":"dependency-of"},{"parent":"61792a3d9f409395","child":"e2e1da9ad39af790","type":"evident-by","metadata":{"kind":"primary"}},{"parent":"654efdcd7ff571d3","child":"a8c63bf4c2aa6af6","type":"dependency-of"},{"parent":"654efdcd7ff571d3","child":"e2e1da9ad39af790","type":"evident-by","metadata":{"kind":"primary"}},{"parent":"6592f001d39c2e5f","child":"882e8b8006958aa7","type":"evident-by","metadata":{"kind":"primary"}},{"parent":"65a81a7b1688b191","child":"a8c63bf4c2aa6af6","type":"dependency-of"},{"parent":"65a81a7b1688b191","child":"e2e1da9ad39af790","type":"evident-by","metadata":{"kind":"primary"}},{"parent":"66baf2235cda475c","child":"a8c63bf4c2aa6af6","type":"dependency-of"},{"parent":"66baf2235cda475c","child":"e2e1da9ad39af790","type":"evident-by","metadata":{"kind":"primary"}},{"parent":"67b8e39e8d72c83b","child":"76ddf373afcb14e6","type":"dependency-of"},{"parent":"67b8e39e8d72c83b","child":"e2e1da9ad39af790","type":"evident-by","metadata":{"kind":"primary"}},{"parent":"68b3ba9ddd5ab654","child":"a8c63bf4c2aa6af6","type":"dependency-of"},{"parent":"68b3ba9ddd5ab654","child":"e2e1da9ad39af790","type":"evident-by","metadata":{"kind":"primary"}},{"parent":"76ddf373afcb14e6","child":"e2e1da9ad39af790","type":"evident-by","metadata":{"kind":"primary"}},{"parent":"7fc119acc1ec15a7","child":"76ddf373afcb14e6","type":"dependency-of"},{"parent":"7fc119acc1ec15a7","child":"e2e1da9ad39af790","type":"evident-by","metadata":{"kind":"primary"}},{"parent":"8b055904f3477773","child":"76ddf373afcb14e6","type":"dependency-of"},{"parent":"8b055904f3477773","child":"e2e1da9ad39af790","type":"evident-by","metadata":{"kind":"primary"}},{"parent":"956ba2c065a0c99d","child":"a8c63bf4c2aa6af6","type":"dependency-of"},{"parent":"956ba2c065a0c99d","child":"e2e1da9ad39af790","type":"evident-by","metadata":{"kind":"primary"}},{"parent":"99be8abfab734041","child":"a8c63bf4c2aa6af6","type":"dependency-of"},{"parent":"99be8abfab734041","child":"e2e1da9ad39af790","type":"evident-by","metadata":{"kind":"primary"}},{"parent":"a5c62215245023bf","child":"76ddf373afcb14e6","type":"dependency-of"},{"parent":"a5c62215245023bf","child":"e2e1da9ad39af790","type":"evident-by","metadata":{"kind":"primary"}},{"parent":"a8c63bf4c2aa6af6","child":"76ddf373afcb14e6","type":"dependency-of"},{"parent":"a8c63bf4c2aa6af6","child":"e2e1da9ad39af790","type":"evident-by","metadata":{"kind":"primary"}},{"parent":"b0e133ed3faac023","child":"a8c63bf4c2aa6af6","type":"dependency-of"},{"parent":"b0e133ed3faac023","child":"e2e1da9ad39af790","type":"evident-by","metadata":{"kind":"primary"}},{"parent":"c8a5569efd83caa5","child":"76ddf373afcb14e6","type":"dependency-of"},{"parent":"c8a5569efd83caa5","child":"e2e1da9ad39af790","type":"evident-by","metadata":{"kind":"primary"}},{"parent":"cf4403db8f648135","child":"a8c63bf4c2aa6af6","type":"dependency-of"},{"parent":"cf4403db8f648135","child":"e2e1da9ad39af790","type":"evident-by","metadata":{"kind":"primary"}},{"parent":"db3c1e8e251c4c2c","child":"67b8e39e8d72c83b","type":"dependency-of"},{"parent":"db3c1e8e251c4c2c","child":"e2e1da9ad39af790","type":"evident-by","metadata":{"kind":"primary"}},{"parent":"f2a933110e480460","child":"76ddf373afcb14e6","type":"dependency-of"},{"parent":"f2a933110e480460","child":"e2e1da9ad39af790","type":"evident-by","metadata":{"kind":"primary"}},{"parent":"f4d28eaf236a9002","child":"5e557fbe1fd5aa47","type":"dependency-of"},{"parent":"f4d28eaf236a9002","child":"e2e1da9ad39af790","type":"evident-by","metadata":{"kind":"primary"}}],"files":[{"id":"1b79f0d7cf6d2743","location":{"path":"/bin/RPMLauncher"},"executable":{"format":"elf","hasExports":false,"hasEntrypoint":false,"importedLibraries":[]},"unknowns":["cargo-auditable-binary-cataloger: rust cataloger: unable to read dependency information: unknown file format","file-executable-cataloger: unable to determine ELF features: EOF","unknowns-labeler: no package identified in executable file"]},{"id":"882e8b8006958aa7","location":{"path":"/bin/data/flutter_assets/packages/dart_discord_rpc/ffi-bin/discord-rpc.dll"},"metadata":{"mode":644,"type":"RegularFile","userID":0,"groupID":0,"mimeType":"application/vnd.microsoft.portable-executable","size":399880},"digests":[{"algorithm":"sha1","value":"ac7bbbdb1d34eb763d8db4ef7875a50f700e9d48"},{"algorithm":"sha256","value":"5cc2e504800cf4ed2f4781364f661ea22349658ddc391b5d54195e573109d87b"}],"executable":{"format":"pe","hasExports":true,"hasEntrypoint":false,"importedLibraries":[]}},{"id":"add5173e4c447468","location":{"path":"/bin/data/flutter_assets/packages/dart_discord_rpc/ffi-bin/libdiscord-rpc.dylib"},"executable":{"format":"macho","hasExports":true,"hasEntrypoint":false,"importedLibraries":["/usr/lib/libSystem.B.dylib","/System/Library/Frameworks/AppKit.framework/Versions/C/AppKit","/usr/lib/libc++.1.dylib","/System/Library/Frameworks/CoreFoundation.framework/Versions/A/CoreFoundation","/System/Library/Frameworks/CoreServices.framework/Versions/A/CoreServices","/System/Library/Frameworks/Foundation.framework/Versions/C/Foundation","/usr/lib/libobjc.A.dylib"]},"unknowns":["unknowns-labeler: no package identified in executable file"]},{"id":"f626384633a8207f","location":{"path":"/bin/data/flutter_assets/packages/dart_discord_rpc/ffi-bin/libdiscord-rpc.so"},"executable":{"format":"elf","hasExports":true,"hasEntrypoint":true,"importedLibraries":["libpthread.so.0","libstdc++.so.6","libm.so.6","libgcc_s.so.1","libc.so.6"],"elfSecurityFeatures":{"symbolTableStripped":false,"stackCanary":false,"nx":true,"relRO":"partial","pie":false,"dso":true,"safeStack":false,"cfi":false,"fortify":false}},"unknowns":["unknowns-labeler: no package identified in executable file"]},{"id":"f28ae4a25be86643","location":{"path":"/bin/lib/libapp.so"},"executable":{"format":"elf","hasExports":false,"hasEntrypoint":false,"importedLibraries":[]},"unknowns":["cargo-auditable-binary-cataloger: rust cataloger: unable to read dependency information: unknown file format","file-executable-cataloger: unable to determine ELF features: EOF","unknowns-labeler: no package identified in executable file"]},{"id":"3978f2c1c31840f1","location":{"path":"/bin/lib/libflutter_linux_gtk.so"},"executable":{"format":"elf","hasExports":false,"hasEntrypoint":false,"importedLibraries":[]},"unknowns":["cargo-auditable-binary-cataloger: rust cataloger: unable to read dependency information: unknown file format","file-executable-cataloger: unable to determine ELF features: EOF","unknowns-labeler: no package identified in executable file"]},{"id":"22aca629e34f9c7f","location":{"path":"/bin/lib/libflutter_window_close_plugin.so"},"executable":{"format":"elf","hasExports":false,"hasEntrypoint":false,"importedLibraries":[]},"unknowns":["cargo-auditable-binary-cataloger: rust cataloger: unable to read dependency information: unknown file format","file-executable-cataloger: unable to determine ELF features: EOF","unknowns-labeler: no package identified in executable file"]},{"id":"16499c17a80d8fb8","location":{"path":"/bin/lib/librpmlauncher_plugin_plugin.so"},"executable":{"format":"elf","hasExports":false,"hasEntrypoint":false,"importedLibraries":[]},"unknowns":["cargo-auditable-binary-cataloger: rust cataloger: unable to read dependency information: unknown file format","file-executable-cataloger: unable to determine ELF features: EOF","unknowns-labeler: no package identified in executable file"]},{"id":"7fc4739f7c684f03","location":{"path":"/bin/lib/libscreen_retriever_plugin.so"},"executable":{"format":"elf","hasExports":false,"hasEntrypoint":false,"importedLibraries":[]},"unknowns":["cargo-auditable-binary-cataloger: rust cataloger: unable to read dependency information: unknown file format","file-executable-cataloger: unable to determine ELF features: EOF","unknowns-labeler: no package identified in executable file"]},{"id":"15dbc56dd5eba662","location":{"path":"/bin/lib/libsentry_flutter_plugin.so"},"executable":{"format":"elf","hasExports":false,"hasEntrypoint":false,"importedLibraries":[]},"unknowns":["cargo-auditable-binary-cataloger: rust cataloger: unable to read dependency information: unknown file format","file-executable-cataloger: unable to determine ELF features: EOF","unknowns-labeler: no package identified in executable file"]},{"id":"f84ed4dc69e87bdc","location":{"path":"/bin/lib/liburl_launcher_linux_plugin.so"},"executable":{"format":"elf","hasExports":false,"hasEntrypoint":false,"importedLibraries":[]},"unknowns":["cargo-auditable-binary-cataloger: rust cataloger: unable to read dependency information: unknown file format","file-executable-cataloger: unable to determine ELF features: EOF","unknowns-labeler: no package identified in executable file"]},{"id":"1a58102f77fe5b7e","location":{"path":"/bin/lib/libwindow_manager_plugin.so"},"executable":{"format":"elf","hasExports":false,"hasEntrypoint":false,"importedLibraries":[]},"unknowns":["cargo-auditable-binary-cataloger: rust cataloger: unable to read dependency information: unknown file format","file-executable-cataloger: unable to determine ELF features: EOF","unknowns-labeler: no package identified in executable file"]},{"id":"14ab1290f8ab6b4a","location":{"path":"/bin/lib/libwindow_size_plugin.so"},"executable":{"format":"elf","hasExports":false,"hasEntrypoint":false,"importedLibraries":[]},"unknowns":["cargo-auditable-binary-cataloger: rust cataloger: unable to read dependency information: unknown file format","file-executable-cataloger: unable to determine ELF features: EOF","unknowns-labeler: no package identified in executable file"]},{"id":"e2e1da9ad39af790","location":{"path":"/test/data/RPMTW-Update-Mod-Fabric-1.18.1-1.3.1.jar"},"metadata":{"mode":644,"type":"RegularFile","userID":0,"groupID":0,"mimeType":"application/jar","size":8807401},"digests":[{"algorithm":"sha1","value":"e2e19d6cd5a453b6417d85208b12742d4000fa39"},{"algorithm":"sha256","value":"9032077e273366d1d0d08dad07f4a852010732c9605ca02fe4effb7eb95a7832"}]}],"source":{"id":"16babd937b1b697d7ec4fecad88e2922094191f04b56cf8320398ca893b7263f","name":"rpmlauncher","version":"0+git.d90db672","type":"snap","metadata":{"summary":"Minecraft Launcher","base":"core20","grade":"stable","confinement":"strict","architectures":["amd64"],"digests":[{"algorithm":"sha256","value":"a9310bd8b25ecaa52f44f8ab4eebfa99c73420cb6a71b6c0f93cb30909329e9a"}]}},"distro":{},"descriptor":{"name":"syft","version":"1.26.1-SNAPSHOT-17b4bf3c","configuration":{"catalogers":{"requested":{"default":["installed","file"]},"used":["alpm-db-cataloger","apk-db-cataloger","binary-classifier-cataloger","bitnami-cataloger","cargo-auditable-binary-cataloger","conan-info-cataloger","dotnet-deps-binary-cataloger","dpkg-db-cataloger","elf-binary-package-cataloger","file-content-cataloger","file-digest-cataloger","file-executable-cataloger","file-metadata-cataloger","go-module-binary-cataloger","graalvm-native-image-cataloger","homebrew-cataloger","java-archive-cataloger","java-jvm-cataloger","javascript-package-cataloger","linux-kernel-cataloger","lua-rock-cataloger","nix-cataloger","pe-binary-package-cataloger","php-composer-installed-cataloger","php-interpreter-cataloger","portage-cataloger","python-installed-package-cataloger","r-package-cataloger","rpm-db-cataloger","ruby-installed-gemspec-cataloger"]},"data-generation":{"generate-cpes":true},"files":{"content":{"globs":null,"skip-files-above-size":0},"hashers":["sha-1","sha-256"],"selection":"owned-by-package"},"licenses":{"coverage":75,"include-content":"none"},"packages":{"binary":["python-binary","python-binary-lib","pypy-binary-lib","go-binary","julia-binary","helm","redis-binary","java-binary-openjdk","java-binary-ibm","java-binary-oracle","java-binary-graalvm","java-binary-jdk","nodejs-binary","go-binary-hint","busybox-binary","util-linux-binary","haproxy-binary","perl-binary","php-composer-binary","httpd-binary","memcached-binary","traefik-binary","arangodb-binary","postgresql-binary","mysql-binary","mysql-binary","mysql-binary","xtrabackup-binary","mariadb-binary","rust-standard-library-linux","rust-standard-library-macos","ruby-binary","erlang-binary","erlang-alpine-binary","erlang-library","swipl-binary","dart-binary","haskell-ghc-binary","haskell-cabal-binary","haskell-stack-binary","consul-binary","nginx-binary","bash-binary","openssl-binary","gcc-binary","fluent-bit-binary","wordpress-cli-binary","curl-binary","lighttpd-binary","proftpd-binary","zstd-binary","xz-binary","gzip-binary","sqlcipher-binary","jq-binary","chrome-binary"],"dotnet":{"dep-packages-must-claim-dll":true,"dep-packages-must-have-dll":false,"propagate-dll-claims-to-parents":true,"relax-dll-claims-when-bundling-detected":true},"golang":{"local-mod-cache-dir":"/home/runner/go/pkg/mod","local-vendor-dir":"","main-module-version":{"from-build-settings":true,"from-contents":false,"from-ld-flags":true},"proxies":["https://proxy.golang.org","direct"],"search-local-mod-cache-licenses":false,"search-local-vendor-licenses":false,"search-remote-licenses":false},"java-archive":{"include-indexed-archives":true,"include-unindexed-archives":false,"maven-base-url":"https://repo1.maven.org/maven2","maven-localrepository-dir":"/home/runner/.m2/repository","max-parent-recursive-depth":0,"resolve-transitive-dependencies":false,"use-maven-localrepository":false,"use-network":false},"javascript":{"include-dev-dependencies":false,"npm-base-url":"https://registry.npmjs.org","search-remote-licenses":false},"linux-kernel":{"catalog-modules":true},"nix":{"capture-owned-files":false},"python":{"guess-unpinned-requirements":false}},"relationships":{"exclude-binary-packages-with-file-ownership-overlap":true,"package-file-ownership":true,"package-file-ownership-overlap":true},"search":{"scope":"squashed"}}},"schema":{"version":"16.0.34","url":"https://raw.githubusercontent.com/anchore/syft/main/schema/json/schema-16.0.34.json"}}
